Workbook

Sheet REPORT_AUG
B2: Meesho August'2026 | Q2: 53 | S2: 43 | T2: 10
B3: Date | C3: Tracking ID Qty | D3: Picklist Qty | E3: Picklist Value | F3: Dispatch Packet | G3: Dispatch % | H3: Disp Tracking QTY | I3: T ID Cancel Qty.Packet | J3: Balance Qty. | K3: Final Disp Qty | L3: Cancel QTY Pcs | M3: Packet/Person | N3: Return From Delivery Qty | O3: Return% | P3: Diff.Despatch Qty | Q3: Diff.Sales Qty | R3: Sale Value Invoice | S3: Invoice Qty | T3: System Return Value | U3: Sys. Return Qty. | V3: Final Sys. Sale Value | W3: Return % Value | X3: Return Damage Qty. | Y3: Return Damage Other Qty. | Z3: Total Qty | AA3: Return Damage Value | AB3: Damage% | AC3: Inventory Value | AD3: Inventory Days | AE3: Total Packer | AF3: OM Associates | AG3: Agency | AH3: Daily Hire | AI3: Sanat Kumar Jana | AJ3: Sushil Kumar Das | AK3: Satya Brata Mallik | AL3: Dillip Kumar Moharana | AM3: Sambit Sahoo | AN3: Sujit Kumar Bhoi | AO3: Pradip Kumar Swain | AP3: Manoj Chhualsingh | AQ3: Sudarsana Sahoo | AR3: Subrat Sahoo | AS3: Bikas | AT3: Pruthwiraj Behera | AU3: Somanatha Behera
B4: 01..08.2026 | C4: 621 | D4: 1019 | E4: 222175.18 | F4: 612 | G4: 0.98550725 | H4: 1008 | I4: 9 | J4: 0 | K4: 612 | L4: 11 | M4: 153 | N4: 45 | O4: 0.073529412 | P4: 0 | Q4: 0 | R4: 218521.41 | S4: 1008 | T4: 47006.76 | U4: 326 | V4: 171514.65 | W4: 0.21511283 | X4: 3 | Y4: 0 | Z4: 3 | AA4: 1701 | AB4: 0.066666667 | AC4: 3954853.4 | AD4: 23.0584 | AE4: 4 | AF4: 4 | AG4: 0 | AH4: 0 | AI4: P | AJ4: P | AK4: P | AL4: P | AM4: P | AN4: P | AO4: P | AP4: P | AQ4: P | AR4: P | AT4: A | AU4: A
B5: 02..08.2026 | C5: 0 | D5: 0 | E5: 0 | G5: #DIV/0! | H5: 0 | I5: 0 | J5: 0 | K5: 0 | L5: 0 | M5: #DIV/0! | N5: 0 | O5: #DIV/0! | P5: 0 | Q5: 0 | R5: 0 | S5: 0 | T5: 0 | U5: 0 | V5: 0 | W5: #DIV/0! | X5: 0 | Y5: 0 | Z5: 0 | AA5: 0 | AB5: #DIV/0! | AC5: 3954853.4 | AD5: #DIV/0! | AE5: 0 | AF5: 0 | AG5: 0 | AH5: 0 | AI5: 0 | AJ5: 0 | AK5: 0 | AL5: 0 | AM5: 0 | AN5: 0 | AO5: 0 | AP5: 0 | AQ5: 0 | AR5: 0 | AT5: 0 | AU5: 0
B6: 03..08.2026 | C6: 2520 | D6: 4249 | E6: 943939.93 | F6: 2496 | G6: 0.99047619 | H6: 4206 | I6: 24 | J6: 0 | K6: 2496 | L6: 43 | M6: 624 | N6: 36 | O6: 0.014423077 | P6: 0 | Q6: 4206 | R6: 0 | S6: 0 | T6: 0 | U6: 0 | V6: 0 | W6: #DIV/0! | X6: 8 | Y6: 0 | Z6: 8 | AA6: 2430.89 | AB6: 0.22222222 | AC6: 3994722.7 | AD6: #DIV/0! | AE6: 4 | AF6: 4 | AG6: 0 | AH6: 0 | AI6: P | AJ6: P | AK6: P | AL6: P | AM6: P | AN6: A | AO6: P | AP6: P | AQ6: P | AR6: P | AT6: A | AU6: A
B7: 04..08.2026 | C7: 749 | D7: 1324 | E7: 234729.93 | F7: 740 | G7: 0.98798398 | H7: 1308 | I7: 9 | J7: 0 | K7: 740 | L7: 16 | M7: 246.66667 | N7: 93 | O7: 0.12567568 | P7: 0 | Q7: -4206 | R7: 1094983.4 | S7: 5514 | T7: 19099.66 | U7: 138 | V7: 1075883.7 | W7: 0.017442877 | X7: 15 | Y7: 0 | Z7: 15 | AA7: 4487.61 | AB7: 0.16129032 | AC7: 4740739.5 | AD7: 4.4063679 | AE7: 3 | AF7: 3 | AG7: 0 | AH7: 0 | AI7: P | AJ7: P | AK7: P | AL7: P | AM7: P | AN7: P | AO7: P | AP7: P | AQ7: P | AR7: A | AT7: A | AU7: A
B8: 05..08.2026 | C8: 1005 | D8: 1640 | E8: 349416.93 | F8: 990 | G8: 0.98507463 | H8: 1617 | I8: 15 | J8: 0 | K8: 990 | L8: 23 | M8: 247.5 | N8: 38 | O8: 0.038383838 | P8: 0 | Q8: 1188 | R8: 95709.79 | S8: 429 | T8: 8190.68 | U8: 81 | V8: 87519.11 | W8: 0.085578288 | X8: 0 | Y8: 0 | Z8: 0 | AA8: 0 | AB8: 0 | AC8: 3954139.6 | AD8: 45.180299 | AE8: 4 | AF8: 4 | AG8: 0 | AH8: 0 | AI8: P | AJ8: P | AK8: P | AL8: P | AM8: P | AN8: P | AO8: P | AP8: P | AQ8: P | AR8: P | AT8: A | AU8: A
B9: 06..08.2026 | C9: 1000 | D9: 1762 | E9: 319570.23 | F9: 969 | G9: 0.969 | H9: 1706 | I9: 31 | J9: 0 | K9: 969 | L9: 56 | M9: 323 | N9: 49 | O9: 0.050567595 | P9: 0 | Q9: -1188 | R9: 559991.59 | S9: 2894 | T9: 1000 | U9: 10 | V9: 558991.59 | W9: 0.0017857411 | X9: 4 | Y9: 0 | Z9: 4 | AA9: 1330.61 | AB9: 0.081632653 | AC9: 4061450.7 | AD9: 7.265674 | AE9: 3 | AF9: 3 | AG9: 0 | AH9: 0 | AI9: P | AJ9: P | AK9: P | AL9: P | AM9: P | AN9: P | AO9: A | AP9: P | AQ9: P | AR9: A | AT9: A | AU9: A
B10: 07..08.2026 | C10: 1062 | D10: 2086 | E10: 310722.03 | F10: 1048 | G10: 0.98681733 | H10: 2067 | I10: 14 | J10: 0 | K10: 1048 | L10: 19 | M10: 349.33333 | N10: 43 | O10: 0.041030534 | P10: 0 | Q10: 0 | R10: 306709.57 | S10: 2067 | T10: 7361.44 | U10: 75 | V10: 299348.13 | W10: 0.024001338 | X10: 4 | Y10: 2 | Z10: 6 | AA10: 863.52 | AB10: 0.13953488 | AC10: 4123744.2 | AD10: 13.775747 | AE10: 3 | AF10: 3 | AG10: 0 | AH10: 0 | AI10: P | AJ10: P | AK10: P | AL10: P | AM10: A | AN10: P | AO10: P | AP10: P | AQ10: P | AR10: P | AT10: A | AU10: A
B11: 08..08.2026 | C11: 1251 | D11: 2517 | E11: 379236.5 | F11: 1216 | G11: 0.97202238 | H11: 2467 | I11: 35 | J11: 0 | K11: 1216 | L11: 50 | M11: 405.33333 | N11: 41 | O11: 0.033717105 | P11: 0 | Q11: 3 | R11: 365225.24 | S11: 2464 | T11: 9489.86 | U11: 46 | V11: 355735.38 | W11: 0.025983582 | X11: 4 | Y11: 1 | Z11: 5 | AA11: 610.79 | AB11: 0.12195122 | AC11: 4533028.8 | AD11: 12.742699 | AE11: 3 | AF11: 3 | AG11: 0 | AH11: 0 | AI11: P | AJ11: P | AK11: P | AL11: P | AM11: A | AN11: P | AO11: P | AP11: P | AQ11: P | AR11: P | AS11: P | AT11: A | AU11: A
B12: 09.08.2026 | C12: 0 | D12: 0 | E12: 0 | G12: #DIV/0! | H12: 0 | I12: 0 | J12: 0 | K12: 0 | L12: 0 | M12: #DIV/0! | N12: 0 | O12: #DIV/0! | P12: 0 | Q12: 0 | R12: 0 | S12: 0 | T12: 0 | U12: 0 | V12: 0 | W12: #DIV/0! | X12: 0 | Y12: 0 | Z12: 0 | AA12: 0 | AB12: #DIV/0! | AC12: 0 | AD12: #DIV/0! | AE12: 0 | AF12: 0 | AG12: 0 | AH12: 0 | AI12: 0 | AJ12: 0 | AK12: 0 | AL12: 0 | AM12: 0 | AN12: 0 | AO12: 0 | AP12: 0 | AQ12: 0 | AR12: 0 | AS12: 0 | AT12: 0 | AU12: 0
B13: 10..08.2026 | C13: 1407 | D13: 2777 | E13: 450847.51 | F13: 1392 | G13: 0.98933902 | H13: 2747 | I13: 15 | J13: 0 | K13: 1392 | L13: 30 | M13: 278.4 | N13: 16 | O13: 0.011494253 | P13: 0 | Q13: 2747 | R13: 0 | S13: 0 | T13: 0 | U13: 0 | V13: 0 | W13: #DIV/0! | X13: 4 | Y13: 0 | Z13: 4 | AA13: 1085.08 | AB13: 0.25 | AC13: 4702058.7 | AD13: #DIV/0! | AE13: 5 | AF13: 5 | AG13: 0 | AH13: 0 | AI13: P | AJ13: P | AK13: P | AL13: P | AM13: P | AN13: P | AO13: P | AP13: P | AQ13: P | AR13: P | AS13: P | AT13: A | AU13: A
B14: 11..08.2026 | C14: 3243 | D14: 6445 | E14: 941886.81 | F14: 3195 | G14: 0.98519889 | H14: 6347 | I14: 48 | J14: 0 | K14: 3195 | L14: 98 | M14: 639 | N14: 103 | O14: 0.032237872 | P14: 0 | Q14: 3610 | R14: 446214.47 | S14: 2737 | T14: 1522.5 | U14: 3 | V14: 444691.97 | W14: 0.0034120364 | X14: 3 | Y14: 1 | Z14: 4 | AA14: 884.29 | AB14: 0.038834951 | AC14: 5406469.5 | AD14: 12.157785 | AE14: 5 | AF14: 5 | AG14: 0 | AH14: 0 | AI14: P | AJ14: P | AK14: P | AL14: P | AM14: P | AN14: P | AO14: P | AP14: P | AQ14: P | AR14: P | AS14: P | AT14: A | AU14: A
B15: 12..08.2026 | C15: 1095 | D15: 1852 | E15: 330682.69 | F15: 1087 | G15: 0.99269406 | H15: 1840 | I15: 8 | J15: 0 | K15: 1087 | L15: 12 | M15: 217.4 | N15: 58 | O15: 0.053357866 | P15: 0 | Q15: -6304 | R15: 1254155.7 | S15: 8144 | T15: 18685.94 | U15: 167 | V15: 1235469.8 | W15: 0.014899218 | X15: 6 | Y15: 0 | Z15: 6 | AA15: 2011.61 | AB15: 0.10344828 | AC15: 5835062.3 | AD15: 4.7229502 | AE15: 5 | AF15: 5 | AG15: 0 | AH15: 0 | AI15: P | AJ15: P | AK15: P | AL15: P | AM15: P | AN15: P | AO15: P | AP15: P | AQ15: P | AR15: P | AS15: P | AT15: A | AU15: A
B16: 13..08.2026 | C16: 1080 | D16: 1879 | E16: 351396.63 | F16: 1065 | G16: 0.98611111 | H16: 1855 | I16: 15 | J16: 0 | K16: 1065 | L16: 24 | M16: 213 | N16: 59 | O16: 0.055399061 | P16: 0 | Q16: -3 | R16: 346913.01 | S16: 1858 | T16: 26483.97 | U16: 148 | V16: 320429.04 | W16: 0.076341818 | X16: 4 | Y16: 0 | Z16: 4 | AA16: 3099.81 | AB16: 0.06779661 | AC16: 4848525 | AD16: 15.131353 | AE16: 5 | AF16: 5 | AG16: 0 | AH16: 0 | AI16: P | AJ16: P | AK16: P | AL16: P | AM16: P | AN16: P | AO16: P | AP16: P | AQ16: P | AR16: P | AS16: P | AT16: A | AU16: A
B17: 14..08.2026 | C17: 890 | D17: 1739 | E17: 295382.58 | F17: 881 | G17: 0.98988764 | H17: 1722 | I17: 9 | J17: 0 | K17: 881 | L17: 17 | M17: 176.2 | N17: 70 | O17: 0.079455165 | P17: 0 | Q17: 0 | R17: 292315.53 | S17: 1722 | T17: 890.34 | U17: 4 | V17: 291425.19 | W17: 0.0030458183 | X17: 1 | Y17: 0 | Z17: 1 | AA17: 285.09 | AB17: 0.014285714 | AC17: 5277377.9 | AD17: 18.10886 | AE17: 5 | AF17: 5 | AG17: 0 | AH17: 0 | AI17: L | AJ17: P | AK17: P | AL17: P | AM17: P | AN17: P | AO17: P | AP17: P | AQ17: P | AR17: P | AS17: P | AT17: A | AU17: A
B18: 15..08.2026 | C18: 0 | D18: 0 | E18: 0 | F18: 0 | G18: #DIV/0! | H18: 0 | I18: 0 | J18: 0 | K18: 0 | L18: 0 | M18: #DIV/0! | N18: 0 | O18: #DIV/0! | P18: 0 | Q18: 0 | R18: 0 | S18: 0 | T18: 35656.3 | U18: 241 | V18: -35656.3 | W18: #DIV/0! | X18: 0 | Y18: 0 | Z18: 0 | AA18: 0 | AB18: #DIV/0! | AC18: 5277377.9 | AD18: -148.00689 | AE18: 0 | AF18: 0 | AG18: 0 | AH18: 0 | AI18: 0 | AJ18: 0 | AK18: 0 | AL18: 0 | AM18: 0 | AN18: 0 | AO18: 0 | AP18: 0 | AQ18: 0 | AR18: 0 | AS18: 0 | AT18: 0 | AU18: 0
B19: 16..08.2026 | C19: 0 | D19: 0 | E19: 0 | F19: 0 | G19: #DIV/0! | H19: 0 | I19: 0 | J19: 0 | K19: 0 | L19: 0 | M19: #DIV/0! | N19: 0 | O19: #DIV/0! | P19: 0 | Q19: 0 | R19: 0 | S19: 0 | T19: 0 | U19: 0 | V19: 0 | W19: #DIV/0! | X19: 0 | Y19: 0 | Z19: 0 | AA19: 0 | AB19: #DIV/0! | AC19: 5277377.9 | AD19: #DIV/0! | AE19: 0 | AF19: 0 | AG19: 0 | AH19: 0 | AI19: 0 | AJ19: 0 | AK19: 0 | AL19: 0 | AM19: 0 | AN19: 0 | AO19: 0 | AP19: 0 | AQ19: 0 | AR19: 0 | AS19: 0 | AT19: 0 | AU19: 0
B20: 17..08.2026 | C20: 2023 | D20: 4057 | E20: 1026445.4 | F20: 1995 | G20: 0.98615917 | H20: 3998 | I20: 28 | J20: 0 | K20: 1995 | L20: 59 | M20: 399 | N20: 138 | O20: 0.069172932 | P20: 0 | Q20: 1455 | R20: 390905.4 | S20: 2543 | T20: 30342.49 | U20: 145 | V20: 360562.91 | W20: 0.077621056 | X20: 15 | Y20: 1 | Z20: 16 | AA20: 4142.11 | AB20: 0.11594203 | AC20: 5097643.6 | AD20: 14.138014 | AE20: 5 | AF20: 5 | AG20: 0 | AH20: 0 | AI20: P | AJ20: P | AK20: P | AL20: P | AM20: P | AN20: P | AO20: P | AP20: P | AQ20: P | AR20: P | AS20: P | AT20: A | AU20: A
B21: 18..08.2026 | G21: #DIV/0! | J21: 0 | K21: 0 | M21: #DIV/0! | O21: #DIV/0! | P21: 0 | Q21: -1455 | R21: 268863.89 | S21: 1455 | T21: 153.5 | U21: 1 | V21: 268710.39 | W21: 0.00057092085 | Z21: 0 | AB21: #DIV/0! | AC21: 4922547.9 | AD21: 18.319157 | AE21: 0 | AG21: 0 | AH21: 0
B22: 19..08.2026 | G22: #DIV/0! | J22: 0 | K22: 0 | M22: #DIV/0! | O22: #DIV/0! | P22: 0 | Q22: 0 | V22: 0 | W22: #DIV/0! | Z22: 0 | AB22: #DIV/0! | AD22: #DIV/0! | AE22: 0 | AG22: 0 | AH22: 0
B23: 20..08.2026 | G23: #DIV/0! | J23: 0 | K23: 0 | M23: #DIV/0! | O23: #DIV/0! | P23: 0 | Q23: 0 | V23: 0 | W23: #DIV/0! | Z23: 0 | AB23: #DIV/0! | AD23: #DIV/0! | AE23: 0 | AG23: 0 | AH23: 0
B24: 21..08.2026 | G24: #DIV/0! | J24: 0 | K24: 0 | M24: #DIV/0! | O24: #DIV/0! | P24: 0 | Q24: 0 | V24: 0 | W24: #DIV/0! | Z24: 0 | AB24: #DIV/0! | AD24: #DIV/0! | AE24: 0 | AG24: 0 | AH24: 0
B25: 22..08.2026 | G25: #DIV/0! | J25: 0 | K25: 0 | M25: #DIV/0! | O25: #DIV/0! | P25: 0 | Q25: 0 | V25: 0 | W25: #DIV/0! | Z25: 0 | AB25: #DIV/0! | AD25: #DIV/0! | AE25: 0 | AG25: 0 | AH25: 0
B26: 23..08.2026 | G26: #DIV/0! | J26: 0 | K26: 0 | M26: #DIV/0! | O26: #DIV/0! | P26: 0 | Q26: 0 | V26: 0 | W26: #DIV/0! | Z26: 0 | AB26: #DIV/0! | AD26: #DIV/0! | AE26: 0 | AG26: 0 | AH26: 0
B27: 24..08.2026 | G27: #DIV/0! | J27: 0 | K27: 0 | M27: #DIV/0! | O27: #DIV/0! | P27: 0 | Q27: 0 | V27: 0 | W27: #DIV/0! | Z27: 0 | AB27: #DIV/0! | AD27: #DIV/0! | AE27: 0 | AG27: 0 | AH27: 0
B28: 25..08.2026 | G28: #DIV/0! | J28: 0 | K28: 0 | M28: #DIV/0! | O28: #DIV/0! | P28: 0 | Q28: 0 | V28: 0 | W28: #DIV/0! | Z28: 0 | AB28: #DIV/0! | AD28: #DIV/0! | AE28: 0 | AG28: 0 | AH28: 0
B29: 26..08.2026 | G29: #DIV/0! | J29: 0 | K29: 0 | M29: #DIV/0! | O29: #DIV/0! | P29: 0 | Q29: 0 | V29: 0 | W29: #DIV/0! | Z29: 0 | AB29: #DIV/0! | AD29: #DIV/0! | AE29: 0 | AG29: 0 | AH29: 0
B30: 27..08.2026 | G30: #DIV/0! | J30: 0 | K30: 0 | M30: #DIV/0! | O30: #DIV/0! | P30: 0 | Q30: 0 | V30: 0 | W30: #DIV/0! | Z30: 0 | AB30: #DIV/0! | AD30: #DIV/0! | AE30: 0 | AG30: 0 | AH30: 0
B31: 28..08.2026 | G31: #DIV/0! | J31: 0 | K31: 0 | M31: #DIV/0! | O31: #DIV/0! | P31: 0 | Q31: 0 | V31: 0 | W31: #DIV/0! | Z31: 0 | AB31: #DIV/0! | AD31: #DIV/0! | AE31: 0 | AG31: 0 | AH31: 0
B32: 29..08.2026 | G32: #DIV/0! | J32: 0 | K32: 0 | M32: #DIV/0! | O32: #DIV/0! | P32: 0 | Q32: 0 | V32: 0 | W32: #DIV/0! | Z32: 0 | AB32: #DIV/0! | AD32: #DIV/0! | AE32: 0 | AG32: 0 | AH32: 0
B33: 30..08.2026 | G33: #DIV/0! | J33: 0 | K33: 0 | M33: #DIV/0! | O33: #DIV/0! | P33: 0 | Q33: 0 | V33: 0 | W33: #DIV/0! | Z33: 0 | AB33: #DIV/0! | AD33: #DIV/0! | AE33: 0 | AG33: 0 | AH33: 0
B34: 31..08.2026 | G34: #DIV/0! | J34: 0 | K34: 0 | M34: #DIV/0! | O34: #DIV/0! | P34: 0 | Q34: 0 | V34: 0 | W34: #DIV/0! | Z34: 0 | AB34: #DIV/0! | AD34: #DIV/0! | AE34: 0 | AG34: 0 | AH34: 0
B35: Total | C35: 17946 | D35: 33346 | E35: 6156432.4 | F35: 17686 | G35: 0.98551209 | I35: 260 | J35: 0 | K35: 17686 | L35: 458 | M35: 327.51852 | N35: 789 | O35: 0.044611557 | P35: 0 | Q35: 53 | R35: 5640509 | S35: 32835 | T35: 205883.44 | U35: 1385 | V35: 5434625.5 | W35: 0.036500862 | X35: 71 | Y35: 5 | Z35: 76 | AA35: 22932.41 | AB35: 0.096324461 | AC35: 79961973 | AD35: 14.713428 | AE35: 54 | AF35: 54 | AG35: 0 | AH35: 0 | AI35: 0 | AJ35: 0 | AK35: 0 | AL35: 0 | AM35: 0 | AN35: 0 | AO35: 0 | AP35: 0 | AQ35: 0 | AR35: 0 | AT35: 0 | AU35: 0
AC36: 4442331.8 | AD36: #DIV/0!
B41: Courior | C41: Tracking | D41: P Quantity | E41: Value | F41: Cancel Qty | G41: Total Qty | H41: Cancel Trc Qty | I41: Dispatch
B42: DELHIVERY | C42: 497 | D42: 945 | E42: 269400.38 | F42: 3 | G42: 942 | H42: 3 | I42: 494
B43: SHADOWFAX | C43: 264 | D43: 526 | E43: 84989.18 | F43: 13 | G43: 513 | H43: 6 | I43: 258
B44: Valmo | C44: 1262 | D44: 2586 | E44: 672055.88 | F44: 43 | G44: 2543 | H44: 19 | I44: 1243
B45: Valmo | G45: 0 | I45: 0
B46: Total | C46: 2023 | D46: 4057 | E46: 1026445.4 | F46: 59 | G46: 3998 | H46: 28 | I46: 1995

Sheet PSR
A1: document_no | B1: apply_to_doc | C1: document_date | D1: apply_to_doc_date | E1: transaction_type | F1: pcode | G1: subbrandform_name | H1: prod_name | I1: quantity
A2: OMNIR-26-I000211 | B2: OMNIR-26-I000211 | C2: 46245 | E2: Sales Invoice | F2: 80864296 | G2: Simply Venus 3s Disp | H2: SV3 1s Pouch 1X192 INR 99 | I2: 6
A3: OMNIR-26-I000211 | B3: OMNIR-26-I000211 | C3: 46245 | E3: Sales Invoice | F3: 80840352 | G3: Venus Breeze Cart 2s | H3: VENUS CG3 CART 2S 1X10X4 INR 475 | I3: 2
A4: OMNIR-26-I000212 | B4: OMNIR-26-I000212 | C4: 46245 | E4: Sales Invoice | F4: 80832389 | G4: Venus Cart 2s | H4: VENUS SMOOTH CART 2S 1X6X4 INR 375 | I4: 1
A5: OMNIR-26-I000211 | B5: OMNIR-26-I000211 | C5: 46245 | E5: Sales Invoice | F5: 80832389 | G5: Venus Cart 2s | H5: VENUS SMOOTH CART 2S 1X6X4 INR 375 | I5: 4
A6: OMNIR-26-I000211 | B6: OMNIR-26-I000211 | C6: 46245 | E6: Sales Invoice | F6: 80875513 | G6: VENUS BIKINI SENSITIVE 1S | H6: SUSINI 1S 1X6X8 INR 175 | I6: 9
A7: OMNIR-26-I000212 | B7: OMNIR-26-I000212 | C7: 46245 | E7: Sales Invoice | F7: 80875513 | G7: VENUS BIKINI SENSITIVE 1S | H7: SUSINI 1S 1X6X8 INR 175 | I7: 1
A8: OMNIR-26-I000212 | B8: OMNIR-26-I000212 | C8: 46245 | E8: Sales Invoice | F8: 80864297 | G8: Venus Skin Love 1s | H8: VENUS SKINLV SENS 1CT 1X12X6 INR 175 | I8: 40
A9: OMNIR-26-I000211 | B9: OMNIR-26-I000211 | C9: 46245 | E9: Sales Invoice | F9: 80864297 | G9: Venus Skin Love 1s | H9: VENUS SKINLV SENS 1CT 1X12X6 INR 175 | I9: 72
A10: OMNIR-26-I000211 | B10: OMNIR-26-I000211 | C10: 46245 | E10: Sales Invoice | F10: 80840354 | G10: Venus Breeze Razor | H10: VENUS CG3 RAZOR 1X18 INR 375 | I10: 7
A11: OMNIR-26-I000212 | B11: OMNIR-26-I000212 | C11: 46245 | E11: Sales Invoice | F11: 80840354 | G11: Venus Breeze Razor | H11: VENUS CG3 RAZOR 1X18 INR 375 | I11: 9
A12: OMNIR-26-I000212 | B12: OMNIR-26-I000212 | C12: 46245 | E12: Sales Invoice | F12: 80832398 | G12: Venus Razor | H12: VENUS SMOOTH RAZOR 1X18 INR 325 | I12: 4
A13: OMNIR-26-I000211 | B13: OMNIR-26-I000211 | C13: 46245 | E13: Sales Invoice | F13: 80832398 | G13: Venus Razor | H13: VENUS SMOOTH RAZOR 1X18 INR 325 | I13: 4
... A447: OMNIR-26-I000214 | B447: OMNIR-26-I000214 | C447: 46246 | E447: Sales Invoice | F447: 80878182 | G447: Olay NA IGF 20gm | H447: OLAY NA IGF 20GX6X8 IN_RS109 PU | I447: 10

Sheet Sheet3
H1: SUB_BRAND | I1: PCODE | J1: EXPECTED | K1: ACTUAL
A2: SUB_BRAND | B2: prod_name | C2: pcode | D2: TOTAL | H2: =VLOOKUP(I2,CHOOSE({1,2},([1]IRA!$D$4:$D$285),[1]IRA!$C$4:$C$285),2,FALSE) -> Cream GIL Lime 93gm | I2: 80862826 | J2: 6 | K2: =IFERROR(VLOOKUP(H2,$A$2:$D$99,4,FALSE),0) -> 6 | L2: =J2-K2 -> 0 | M2: =IFERROR(L2=0,"CHECK") -> TRUE
A3: =VLOOKUP(C3,PSR!$F$1:$G$447,2,FALSE) -> Simply Venus 3s Disp | B3: SV3 1s Pouch 1X192 INR 99 | C3: 80864296 | D3: =SUMIF(PSR!$G$2:$G$447,Sheet3!A3,PSR!$I$2:$I$447) -> 24 | H3: =VLOOKUP(I3,CHOOSE({1,2},([1]IRA!$D$4:$D$285),[1]IRA!$C$4:$C$285),2,FALSE) -> AS SPLSH (RB) 50ML | I3: 80865298 | J3: 2 | K3: =IFERROR(VLOOKUP(H3,$A$2:$D$99,4,FALSE),0) -> 2 | L3: =J3-K3 -> 0 | M3: =IFERROR(L3=0,"CHECK") -> TRUE
A4: =VLOOKUP(C4,PSR!$F$1:$G$447,2,FALSE) -> Venus Breeze Cart 2s | B4: VENUS CG3 CART 2S 1X10X4 INR 475 | C4: 80840352 | D4: =SUMIF(PSR!$G$2:$G$447,Sheet3!A4,PSR!$I$2:$I$447) -> 25 | H4: =VLOOKUP(I4,CHOOSE({1,2},([1]IRA!$D$4:$D$285),[1]IRA!$C$4:$C$285),2,FALSE) -> Guard R+8 Promo Pack | I4: 83904003 | J4: 152 | K4: =IFERROR(VLOOKUP(H4,$A$2:$D$99,4,FALSE),0) -> 152 | L4: =J4-K4 -> 0 | M4: =IFERROR(L4=0,"CHECK") -> TRUE
A5: =VLOOKUP(C5,PSR!$F$1:$G$447,2,FALSE) -> Venus Cart 2s | B5: VENUS SMOOTH CART 2S 1X6X4 INR 375 | C5: 80832389 | D5: =SUMIF(PSR!$G$2:$G$447,Sheet3!A5,PSR!$I$2:$I$447) -> 8 | H5: =VLOOKUP(I5,CHOOSE({1,2},([1]IRA!$D$4:$D$285),[1]IRA!$C$4:$C$285),2,FALSE) -> Foam (Reg) 50gm | I5: 80866726 | J5: 18 | K5: =IFERROR(VLOOKUP(H5,$A$2:$D$99,4,FALSE),0) -> 18 | L5: =J5-K5 -> 0 | M5: =IFERROR(L5=0,"CHECK") -> TRUE
A6: =VLOOKUP(C6,PSR!$F$1:$G$447,2,FALSE) -> VENUS BIKINI SENSITIVE 1S | B6: SUSINI 1S 1X6X8 INR 175 | C6: 80875513 | D6: =SUMIF(PSR!$G$2:$G$447,Sheet3!A6,PSR!$I$2:$I$447) -> 56 | H6: =VLOOKUP(I6,CHOOSE({1,2},([1]IRA!$D$4:$D$285),[1]IRA!$C$4:$C$285),2,FALSE) -> Fusion Power Raz | I6: 80797472 | J6: 1 | K6: =IFERROR(VLOOKUP(H6,$A$2:$D$99,4,FALSE),0) -> 1 | L6: =J6-K6 -> 0 | M6: =IFERROR(L6=0,"CHECK") -> TRUE
A7: =VLOOKUP(C7,PSR!$F$1:$G$447,2,FALSE) -> Venus Skin Love 1s | B7: VENUS SKINLV SENS 1CT 1X12X6 INR 175 | C7: 80864297 | D7: =SUMIF(PSR!$G$2:$G$447,Sheet3!A7,PSR!$I$2:$I$447) -> 629 | H7: =VLOOKUP(I7,CHOOSE({1,2},([1]IRA!$D$4:$D$285),[1]IRA!$C$4:$C$285),2,FALSE) -> Fusion Raz | I7: 80797470 | J7: 3 | K7: =IFERROR(VLOOKUP(H7,$A$2:$D$99,4,FALSE),0) -> 3 | L7: =J7-K7 -> 0 | M7: =IFERROR(L7=0,"CHECK") -> TRUE
A8: =VLOOKUP(C8,PSR!$F$1:$G$447,2,FALSE) -> Venus Breeze Razor | B8: VENUS CG3 RAZOR 1X18 INR 375 | C8: 80840354 | D8: =SUMIF(PSR!$G$2:$G$447,Sheet3!A8,PSR!$I$2:$I$447) -> 50 | H8: =VLOOKUP(I8,CHOOSE({1,2},([1]IRA!$D$4:$D$285),[1]IRA!$C$4:$C$285),2,FALSE) -> Guard 3in1 Cart 2s | I8: 80867316 | J8: 18 | K8: =IFERROR(VLOOKUP(H8,$A$2:$D$99,4,FALSE),0) -> 18 | L8: =J8-K8 -> 0 | M8: =IFERROR(L8=0,"CHECK") -> TRUE
A9: =VLOOKUP(C9,PSR!$F$1:$G$447,2,FALSE) -> Venus Razor | B9: VENUS SMOOTH RAZOR 1X18 INR 325 | C9: 80832398 | D9: =SUMIF(PSR!$G$2:$G$447,Sheet3!A9,PSR!$I$2:$I$447) -> 30 | H9: =VLOOKUP(I9,CHOOSE({1,2},([1]IRA!$D$4:$D$285),[1]IRA!$C$4:$C$285),2,FALSE) -> Guard Cream 125 gm | I9: 80896468 | J9: 60 | K9: =IFERROR(VLOOKUP(H9,$A$2:$D$99,4,FALSE),0) -> 60 | L9: =J9-K9 -> 0 | M9: =IFERROR(L9=0,"CHECK") -> TRUE
A10: =VLOOKUP(C10,PSR!$F$1:$G$447,2,FALSE) -> Venus Snap 1UP | B10: VENUS SNAP RAZOR 1X24 INR 425 | C10: 80832394 | D10: =SUMIF(PSR!$G$2:$G$447,Sheet3!A10,PSR!$I$2:$I$447) -> 13 | H10: =VLOOKUP(I10,CHOOSE({1,2},([1]IRA!$D$4:$D$285),[1]IRA!$C$4:$C$285),2,FALSE) -> Mach 3 Cart 2s | I10: 80876082 | J10: 14 | K10: =IFERROR(VLOOKUP(H10,$A$2:$D$99,4,FALSE),0) -> 14 | L10: =J10-K10 -> 0 | M10: =IFERROR(L10=0,"CHECK") -> TRUE
A11: =VLOOKUP(C11,PSR!$F$1:$G$447,2,FALSE) -> Guard 3in1 Cart 2s | B11: GUARD 3IN1 690 CT2 1X12X6 INR 99 | C11: 80867316 | D11: =SUMIF(PSR!$G$2:$G$447,Sheet3!A11,PSR!$I$2:$I$447) -> 18 | H11: =VLOOKUP(I11,CHOOSE({1,2},([1]IRA!$D$4:$D$285),[1]IRA!$C$4:$C$285),2,FALSE) -> Mach-3 Charcoal Rzr | I11: 80803710 | J11: 4 | K11: =IFERROR(VLOOKUP(H11,$A$2:$D$99,4,FALSE),0) -> 4 | L11: =J11-K11 -> 0 | M11: =IFERROR(L11=0,"CHECK") -> TRUE
A12: =VLOOKUP(C12,PSR!$F$1:$G$447,2,FALSE) -> Guard R+8 Promo Pack | B12: GUARD R+8CT 1X12X10 133 INR | C12: 83904003 | D12: =SUMIF(PSR!$G$2:$G$447,Sheet3!A12,PSR!$I$2:$I$447) -> 152 | H12: =VLOOKUP(I12,CHOOSE({1,2},([1]IRA!$D$4:$D$285),[1]IRA!$C$4:$C$285),2,FALSE) -> Cream GIL Reg 93gm | I12: 80862828 | J12: 9 | K12: =IFERROR(VLOOKUP(H12,$A$2:$D$99,4,FALSE),0) -> 9 | L12: =J12-K12 -> 0 | M12: =IFERROR(L12=0,"CHECK") -> TRUE
A13: =VLOOKUP(C13,PSR!$F$1:$G$447,2,FALSE) -> Mach 3 Cart 2s | B13: MACH3 PPH CART 2S 1X6X12 INR 349 | C13: 80876082 | D13: =SUMIF(PSR!$G$2:$G$447,Sheet3!A13,PSR!$I$2:$I$447) -> 14 | H13: =VLOOKUP(I13,CHOOSE({1,2},([1]IRA!$D$4:$D$285),[1]IRA!$C$4:$C$285),2,FALSE) -> TSG (Sen) 60g | I13: 80753181 | J13: 3 | K13: =IFERROR(VLOOKUP(H13,$A$2:$D$99,4,FALSE),0) -> 3 | L13: =J13-K13 -> 0 | M13: =IFERROR(L13=0,"CHECK") -> TRUE
A14: =VLOOKUP(C14,PSR!$F$1:$G$447,2,FALSE) -> Mach-3 Charcoal Rzr | B14: MACH3 CHAR RAZ1UP F1 1X6X6 349 INR | C14: 80803710 | D14: =SUMIF(PSR!$G$2:$G$447,Sheet3!A14,PSR!$I$2:$I$447) -> 4 | H14: =VLOOKUP(I14,CHOOSE({1,2},([1]IRA!$D$4:$D$285),[1]IRA!$C$4:$C$285),2,FALSE) -> Foam (Reg) 200ml | I14: 80866724 | J14: 1 | K14: =IFERROR(VLOOKUP(H14,$A$2:$D$99,4,FALSE),0) -> 1 | L14: =J14-K14 -> 0 | M14: =IFERROR(L14=0,"CHECK") -> TRUE
... A22: =VLOOKUP(C22,PSR!$F$1:$G$447,2,FALSE) -> Fat Foamy (Sen) 300gm | B22: FMY FM SHVP 418G SENS 1X12 INR 290 | C22: 80866723 | D22: =SUMIF(PSR!$G$2:$G$447,Sheet3!A22,PSR!$I$2:$I$447) -> 158 | H22: =VLOOKUP(I22,CHOOSE({1,2},([1]IRA!$D$4:$D$285),[1]IRA!$C$4:$C$285),2,FALSE) -> Simply Venus 3s Disp | I22: 80864296 | J22: 24 | K22: =IFERROR(VLOOKUP(H22,$A$2:$D$99,4,FALSE),0) -> 24 | L22: =J22-K22 -> 0 | M22: =IFERROR(L22=0,"CHECK") -> TRUE
A23: =VLOOKUP(C23,PSR!$F$1:$G$447,2,FALSE) -> Foam (Charcoal) 200ml | B23: GIL FM SHVP 196 G CHAR 1X24 INR 270 | C23: 80866728 | D23: =SUMIF(PSR!$G$2:$G$447,Sheet3!A23,PSR!$I$2:$I$447) -> 5 | H23: Venus Skin Love 1s | I23: 80864297 | J23: 629 | K23: =IFERROR(VLOOKUP(H23,$A$2:$D$99,4,FALSE),0) -> 629 | L23: =J23-K23 -> 0 | M23: =IFERROR(L23=0,"CHECK") -> TRUE
A24: =VLOOKUP(C24,PSR!$F$1:$G$447,2,FALSE) -> Foam (Lmn) 200ml | B24: GIL FM SHVP 196 G LMNL 1X24 INR 270 | C24: 80866725 | D24: =SUMIF(PSR!$G$2:$G$447,Sheet3!A24,PSR!$I$2:$I$447) -> 5 | H24: =VLOOKUP(I24,CHOOSE({1,2},([1]IRA!$D$4:$D$285),[1]IRA!$C$4:$C$285),2,FALSE) -> Venus Cart 2s | I24: 80832389 | J24: 8 | K24: =IFERROR(VLOOKUP(H24,$A$2:$D$99,4,FALSE),0) -> 8 | L24: =J24-K24 -> 0 | M24: =IFERROR(L24=0,"CHECK") -> TRUE
A25: =VLOOKUP(C25,PSR!$F$1:$G$447,2,FALSE) -> Foam (Reg) 50gm | B25: FMY FM SHVP 50 G REG 1X48 INR 95 | C25: 80866726 | D25: =SUMIF(PSR!$G$2:$G$447,Sheet3!A25,PSR!$I$2:$I$447) -> 18 | H25: =VLOOKUP(I25,CHOOSE({1,2},([1]IRA!$D$4:$D$285),[1]IRA!$C$4:$C$285),2,FALSE) -> Venus Razor | I25: 80832398 | J25: 30 | K25: =IFERROR(VLOOKUP(H25,$A$2:$D$99,4,FALSE),0) -> 30 | L25: =J25-K25 -> 0 | M25: =IFERROR(L25=0,"CHECK") -> TRUE
A26: =VLOOKUP(C26,PSR!$F$1:$G$447,2,FALSE) -> Cream GIL Reg 93gm | B26: GIL REGULAR SHV CRM 70G 1X96 80INR | C26: 80862828 | D26: =SUMIF(PSR!$G$2:$G$447,Sheet3!A26,PSR!$I$2:$I$447) -> 9 | H26: =VLOOKUP(I26,CHOOSE({1,2},([1]IRA!$D$4:$D$285),[1]IRA!$C$4:$C$285),2,FALSE) -> Venus Snap 1UP | I26: 80832394 | J26: 13 | K26: =IFERROR(VLOOKUP(H26,$A$2:$D$99,4,FALSE),0) -> 13 | L26: =J26-K26 -> 0 | M26: =IFERROR(L26=0,"CHECK") -> TRUE
A27: =VLOOKUP(C27,PSR!$F$1:$G$447,2,FALSE) -> Guard Cream 125 gm | B27: GUARD CREAM 125G 1X72 INR62 | C27: 80896468 | D27: =SUMIF(PSR!$G$2:$G$447,Sheet3!A27,PSR!$I$2:$I$447) -> 60 | H27: =VLOOKUP(I27,CHOOSE({1,2},([1]IRA!$D$4:$D$285),[1]IRA!$C$4:$C$285),2,FALSE) -> H&S AHF 90ML | I27: 83911270 | J27: 231 | K27: =IFERROR(VLOOKUP(H27,$A$2:$D$99,4,FALSE),0) -> 231 | L27: =J27-K27 -> 0 | M27: =IFERROR(L27=0,"CHECK") -> TRUE
A28: =VLOOKUP(C28,PSR!$F$1:$G$447,2,FALSE) -> whspr Choice ON XXL 6s | B28: WHI CHOICE NGTS T5 6X64 (55) SCENT | C28: 80869896 | D28: =SUMIF(PSR!$G$2:$G$447,Sheet3!A28,PSR!$I$2:$I$447) -> 450 | H28: =VLOOKUP(I28,CHOOSE({1,2},([1]IRA!$D$4:$D$285),[1]IRA!$C$4:$C$285),2,FALSE) -> H&S CM 90ML | I28: 80892904 | J28: 414 | K28: =IFERROR(VLOOKUP(H28,$A$2:$D$99,4,FALSE),0) -> 414 | L28: =J28-K28 -> 0 | M28: =IFERROR(L28=0,"CHECK") -> TRUE
A29: =VLOOKUP(C29,PSR!$F$1:$G$447,2,FALSE) -> whspr Choice Wings 6s | B29: WHSPR CHOICE T1 RG WGS 6X126 (40) | C29: 83911777 | D29: =SUMIF(PSR!$G$2:$G$447,Sheet3!A29,PSR!$I$2:$I$447) -> 220 | H29: =VLOOKUP(I29,CHOOSE({1,2},([1]IRA!$D$4:$D$285),[1]IRA!$C$4:$C$285),2,FALSE) -> H&S SS 90ML | I29: 83911280 | J29: 171 | K29: =IFERROR(VLOOKUP(H29,$A$2:$D$99,4,FALSE),0) -> 171 | L29: =J29-K29 -> 0 | M29: =IFERROR(L29=0,"CHECK") -> TRUE
H30: =VLOOKUP(I30,CHOOSE({1,2},([1]IRA!$D$4:$D$285),[1]IRA!$C$4:$C$285),2,FALSE) -> H&S 2in1 SS 72ml | I30: 80880909 | J30: 87 | K30: =IFERROR(VLOOKUP(H30,$A$2:$D$99,4,FALSE),0) -> 96 | L30: =J30-K30 -> -9 | M30: =IFERROR(L30=0,"CHECK") -> FALSE
A31: =VLOOKUP(C31,PSR!$F$1:$G$447,2,FALSE) -> whspr Choice Ultra 6s | B31: WHP CHOICE ULT S3 EJ 6X112 (50) SCENT | C31: 83911635 | D31: =SUMIF(PSR!$G$2:$G$447,Sheet3!A31,PSR!$I$2:$I$447) -> 2584 | H31: =VLOOKUP(I31,CHOOSE({1,2},([1]IRA!$D$4:$D$285),[1]IRA!$C$4:$C$285),2,FALSE) -> H&S 7IN1 72ML | I31: 83911276 | J31: 33 | K31: =IFERROR(VLOOKUP(H31,$A$2:$D$99,4,FALSE),0) -> 33 | L31: =J31-K31 -> 0 | M31: =IFERROR(L31=0,"CHECK") -> TRUE
A32: =VLOOKUP(C32,PSR!$F$1:$G$447,2,FALSE) -> whspr Choice XL 6s | B32: WHSPR CHOICE T3 6X120 (45) PINHOLE | C32: 83911783 | D32: =SUMIF(PSR!$G$2:$G$447,Sheet3!A32,PSR!$I$2:$I$447) -> 200 | H32: =VLOOKUP(I32,CHOOSE({1,2},([1]IRA!$D$4:$D$285),[1]IRA!$C$4:$C$285),2,FALSE) -> H&S BG 72ML | I32: 83911281 | J32: 123 | K32: =IFERROR(VLOOKUP(H32,$A$2:$D$99,4,FALSE),0) -> 123 | L32: =J32-K32 -> 0 | M32: =IFERROR(L32=0,"CHECK") -> TRUE
A33: =VLOOKUP(C33,PSR!$F$1:$G$447,2,FALSE) -> Whspr ON Koala Pants L-XL 6s | B33: WHISPER PERIOD PANTS L/XL 6CTX18 CI | C33: 80870358 | D33: =SUMIF(PSR!$G$2:$G$447,Sheet3!A33,PSR!$I$2:$I$447) -> 81 | H33: =VLOOKUP(I33,CHOOSE({1,2},([1]IRA!$D$4:$D$285),[1]IRA!$C$4:$C$285),2,FALSE) -> OB Crisscross Bact Blast B2G1 Sft | I33: 80894418 | J33: 2 | K33: =IFERROR(VLOOKUP(H33,$A$2:$D$99,4,FALSE),0) -> 2 | L33: =J33-K33 -> 0 | M33: =IFERROR(L33=0,"CHECK") -> TRUE
A34: =VLOOKUP(C34,PSR!$F$1:$G$447,2,FALSE) -> Whspr ON Koala Pants M-L 6s | B34: WHISPER PERIOD PANTS M/L 6CTX18 CI | C34: 80870357 | D34: =SUMIF(PSR!$G$2:$G$447,Sheet3!A34,PSR!$I$2:$I$447) -> 178 | H34: =VLOOKUP(I34,CHOOSE({1,2},([1]IRA!$D$4:$D$285),[1]IRA!$C$4:$C$285),2,FALSE) -> Olay NA IGF 20gm | I34: 80878182 | J34: 42 | K34: =IFERROR(VLOOKUP(H34,$A$2:$D$99,4,FALSE),0) -> 42 | L34: =J34-K34 -> 0 | M34: =IFERROR(L34=0,"CHECK") -> TRUE
A35: =VLOOKUP(C35,PSR!$F$1:$G$447,2,FALSE) -> whspr Ult ON XXL+ 6s | B35: WHSPR ULT NGT XXL+ S7AB 6X54 (150) MD | C35: 83908992 | D35: =SUMIF(PSR!$G$2:$G$447,Sheet3!A35,PSR!$I$2:$I$447) -> 2 | H35: =VLOOKUP(I35,CHOOSE({1,2},([1]IRA!$D$4:$D$285),[1]IRA!$C$4:$C$285),2,FALSE) -> OS POCKET STREAMER OF 2 LIONPRIDE | I35: 80762958 | J35: 1 | K35: =IFERROR(VLOOKUP(H35,$A$2:$D$99,4,FALSE),0) -> 1 | L35: =J35-K35 -> 0 | M35: =IFERROR(L35=0,"CHECK") -> TRUE
A36: =VLOOKUP(C36,PSR!$F$1:$G$447,2,FALSE) -> whspr Ult XXXL ON 4s | B36: WHP ULT NGT XXXL T9 4X36 (150) PU INDIA | C36: 80887674 | D36: =SUMIF(PSR!$G$2:$G$447,Sheet3!A36,PSR!$I$2:$I$447) -> 24 | H36: =VLOOKUP(I36,CHOOSE({1,2},([1]IRA!$D$4:$D$285),[1]IRA!$C$4:$C$285),2,FALSE) -> OB CAVDEF NEEM SFT4 | I36: 80895603 | J36: 6 | K36: =IFERROR(VLOOKUP(H36,$A$2:$D$99,4,FALSE),0) -> 6 | L36: =J36-K36 -> 0 | M36: =IFERROR(L36=0,"CHECK") -> TRUE
A37: =VLOOKUP(C37,PSR!$F$1:$G$447,2,FALSE) -> whspr Maxi Rg 15s | B37: WHSPR T2 MAXI FIT REG NWGS 15X45 (220) | C37: 80869511 | D37: =SUMIF(PSR!$G$2:$G$447,Sheet3!A37,PSR!$I$2:$I$447) -> 11 | H37: =VLOOKUP(I37,CHOOSE({1,2},([1]IRA!$D$4:$D$285),[1]IRA!$C$4:$C$285),2,FALSE) -> OB KIDS CHOTA BHEEM 3S | I37: 80895602 | J37: 16 | K37: =IFERROR(VLOOKUP(H37,$A$2:$D$99,4,FALSE),0) -> 16 | L37: =J37-K37 -> 0 | M37: =IFERROR(L37=0,"CHECK") -> TRUE
A38: =VLOOKUP(C38,PSR!$F$1:$G$447,2,FALSE) -> whspr Ultra XL+ 7s CFC | B38: WHSPR ULT LCC+ XL+ WGS 7X64 | C38: 80893410 | D38: =SUMIF(PSR!$G$2:$G$447,Sheet3!A38,PSR!$I$2:$I$447) -> 99 | H38: =VLOOKUP(I38,CHOOSE({1,2},([1]IRA!$D$4:$D$285),[1]IRA!$C$4:$C$285),2,FALSE) -> #N/A | I38: 80895783 | J38: 4 | K38: =IFERROR(VLOOKUP(H38,$A$2:$D$99,4,FALSE),0) -> 0 | L38: =J38-K38 -> 4 | M38: =IFERROR(L38=0,"CHECK") -> FALSE
A39: =VLOOKUP(C39,PSR!$F$1:$G$447,2,FALSE) -> whspr Ult ON XXL 7s | B39: WHSPR ULT BIN NGT XXL 7X48 (115) PU__ | C39: 83916746 | D39: =SUMIF(PSR!$G$2:$G$447,Sheet3!A39,PSR!$I$2:$I$447) -> 57 | H39: =VLOOKUP(I39,CHOOSE({1,2},([1]IRA!$D$4:$D$285),[1]IRA!$C$4:$C$285),2,FALSE) -> Active Baby SM Econ | I39: 80895465 | J39: 29 | K39: =IFERROR(VLOOKUP(H39,$A$2:$D$99,4,FALSE),0) -> 29 | L39: =J39-K39 -> 0 | M39: =IFERROR(L39=0,"CHECK") -> TRUE
A40: =VLOOKUP(C40,PSR!$F$1:$G$447,2,FALSE) -> BabyRub 25 ml | B40: VICKS BABYRUB 25MLX9X24 JAR INR117 | C40: 80862572 | D40: =SUMIF(PSR!$G$2:$G$447,Sheet3!A40,PSR!$I$2:$I$447) -> 4 | H40: =VLOOKUP(I40,CHOOSE({1,2},([1]IRA!$D$4:$D$285),[1]IRA!$C$4:$C$285),2,FALSE) -> PC Pants LG Econ Pk | I40: 83921920 | J40: 28 | K40: =IFERROR(VLOOKUP(H40,$A$2:$D$99,4,FALSE),0) -> 28 | L40: =J40-K40 -> 0 | M40: =IFERROR(L40=0,"CHECK") -> TRUE
A41: =VLOOKUP(C41,PSR!$F$1:$G$447,2,FALSE) -> Vaporub 25gm | B41: VICKS VAPORUB CL 25 MLX24X16 RS109 | C41: 83916219 | D41: =SUMIF(PSR!$G$2:$G$447,Sheet3!A41,PSR!$I$2:$I$447) -> 8 | H41: =VLOOKUP(I41,CHOOSE({1,2},([1]IRA!$D$4:$D$285),[1]IRA!$C$4:$C$285),2,FALSE) -> RED Pants Jumbo New LG | I41: 80887983 | J41: 6 | K41: =IFERROR(VLOOKUP(H41,$A$2:$D$99,4,FALSE),0) -> 45 | L41: =J41-K41 -> -39 | M41: =IFERROR(L41=0,"CHECK") -> FALSE
A42: =VLOOKUP(C42,PSR!$F$1:$G$447,2,FALSE) -> ATOM ORIGINAL 150ML | B42: OS ASL ATOMIZER ORIG 150MLX24 S3_RS349 | C42: 80830411 | D42: =SUMIF(PSR!$G$2:$G$447,Sheet3!A42,PSR!$I$2:$I$447) -> 6 | H42: PC Pants MD Econ Pk | I42: 83921921 | J42: 115 | K42: =IFERROR(VLOOKUP(H42,$A$2:$D$99,4,FALSE),0) -> 115 | L42: =J42-K42 -> 0 | M42: =IFERROR(L42=0,"CHECK") -> TRUE
A43: =VLOOKUP(C43,PSR!$F$1:$G$447,2,FALSE) -> AmbPr Air LB | B43: AMBI LEGO AIR SPRAY 275mlX6 LB | C43: 80780342 | D43: =SUMIF(PSR!$G$2:$G$447,Sheet3!A43,PSR!$I$2:$I$447) -> 1 | H43: =VLOOKUP(I43,CHOOSE({1,2},([1]IRA!$D$4:$D$285),[1]IRA!$C$4:$C$285),2,FALSE) -> RED Pants Jumbo New MD | I43: 83918762 | J43: 90 | K43: =IFERROR(VLOOKUP(H43,$A$2:$D$99,4,FALSE),0) -> 90 | L43: =J43-K43 -> 0 | M43: =IFERROR(L43=0,"CHECK") -> TRUE
A44: =VLOOKUP(C44,PSR!$F$1:$G$447,2,FALSE) -> Active Baby NB Econ | B44: PAMPERS DPR M5 NB24SX18 ECON GS PU IN | C44: 83933413 | D44: =SUMIF(PSR!$G$2:$G$447,Sheet3!A44,PSR!$I$2:$I$447) -> 252 | H44: PC Pants NB Econ Pk | I44: 83921924 | J44: 171 | K44: =IFERROR(VLOOKUP(H44,$A$2:$D$99,4,FALSE),0) -> 171 | L44: =J44-K44 -> 0 | M44: =IFERROR(L44=0,"CHECK") -> TRUE
A45: =VLOOKUP(C45,PSR!$F$1:$G$447,2,FALSE) -> Active Baby SM Econ | B45: PAMPERS DPR M5 SM22SX18 ECON GS IN | C45: 80895465 | D45: =SUMIF(PSR!$G$2:$G$447,Sheet3!A45,PSR!$I$2:$I$447) -> 29 | H45: =VLOOKUP(I45,CHOOSE({1,2},([1]IRA!$D$4:$D$285),[1]IRA!$C$4:$C$285),2,FALSE) -> PC Pants SM Econ Pk | I45: 83921923 | J45: 75 | K45: =IFERROR(VLOOKUP(H45,$A$2:$D$99,4,FALSE),0) -> 75 | L45: =J45-K45 -> 0 | M45: =IFERROR(L45=0,"CHECK") -> TRUE
H46: =VLOOKUP(I46,CHOOSE({1,2},([1]IRA!$D$4:$D$285),[1]IRA!$C$4:$C$285),2,FALSE) -> PC Pants XL Econ PK | I46: 80887692 | J46: 12 | K46: =IFERROR(VLOOKUP(H46,$A$2:$D$99,4,FALSE),0) -> 12 | L46: =J46-K46 -> 0 | M46: =IFERROR(L46=0,"CHECK") -> TRUE
A47: =VLOOKUP(C47,PSR!$F$1:$G$447,2,FALSE) -> RED Pants Jumbo New MD | B47: PAMPERS PANTS DL2 MD48SX6 JP KN2 PU NMIN | C47: 83918762 | D47: =SUMIF(PSR!$G$2:$G$447,Sheet3!A47,PSR!$I$2:$I$447) -> 90 | H47: =VLOOKUP(I47,CHOOSE({1,2},([1]IRA!$D$4:$D$285),[1]IRA!$C$4:$C$285),2,FALSE) -> BLUE Pants Regs MD | I47: 80895502 | J47: 6 | K47: =IFERROR(VLOOKUP(H47,$A$2:$D$99,4,FALSE),0) -> 6 | L47: =J47-K47 -> 0 | M47: =IFERROR(L47=0,"CHECK") -> TRUE
A48: =VLOOKUP(C48,PSR!$F$1:$G$447,2,FALSE) -> RED Pants Jumbo New SM | B48: PAMPERS PANTS DL2 SM60SX6 JP KN2PU CCIN | C48: 83918765 | D48: =SUMIF(PSR!$G$2:$G$447,Sheet3!A48,PSR!$I$2:$I$447) -> 1206 | H48: =VLOOKUP(I48,CHOOSE({1,2},([1]IRA!$D$4:$D$285),[1]IRA!$C$4:$C$285),2,FALSE) -> BLUE Pants Regs NB | I48: 80895500 | J48: 21 | K48: =IFERROR(VLOOKUP(H48,$A$2:$D$99,4,FALSE),0) -> 21 | L48: =J48-K48 -> 0 | M48: =IFERROR(L48=0,"CHECK") -> TRUE
A49: =VLOOKUP(C49,PSR!$F$1:$G$447,2,FALSE) -> RED Pants Regs LG | B49: PAMPERS PANTS DL2 LG7SX40 REG KNGS SO IN | C49: 83912164 | D49: =SUMIF(PSR!$G$2:$G$447,Sheet3!A49,PSR!$I$2:$I$447) -> 351 | H49: =VLOOKUP(I49,CHOOSE({1,2},([1]IRA!$D$4:$D$285),[1]IRA!$C$4:$C$285),2,FALSE) -> BLUE Pants Regs SM | I49: 83912172 | J49: 159 | K49: =IFERROR(VLOOKUP(H49,$A$2:$D$99,4,FALSE),0) -> 159 | L49: =J49-K49 -> 0 | M49: =IFERROR(L49=0,"CHECK") -> TRUE
A50: =VLOOKUP(C50,PSR!$F$1:$G$447,2,FALSE) -> RED Pants Regs MD | B50: PAMPERS PANTS DL2 MD8SX40 REG KNGS SO IN | C50: 83912166 | D50: =SUMIF(PSR!$G$2:$G$447,Sheet3!A50,PSR!$I$2:$I$447) -> 327 | H50: =VLOOKUP(I50,CHOOSE({1,2},([1]IRA!$D$4:$D$285),[1]IRA!$C$4:$C$285),2,FALSE) -> BLUE Pants Regs XL | I50: 80895504 | J50: 10 | K50: =IFERROR(VLOOKUP(H50,$A$2:$D$99,4,FALSE),0) -> 10 | L50: =J50-K50 -> 0 | M50: =IFERROR(L50=0,"CHECK") -> TRUE
A51: =VLOOKUP(C51,PSR!$F$1:$G$447,2,FALSE) -> RED Pants Regs NB | B51: PAMPERS PANTS DL2 XS10SX40 REG KN2 PU IN | C51: 83918758 | D51: =SUMIF(PSR!$G$2:$G$447,Sheet3!A51,PSR!$I$2:$I$447) -> 99 | H51: =VLOOKUP(I51,CHOOSE({1,2},([1]IRA!$D$4:$D$285),[1]IRA!$C$4:$C$285),2,FALSE) -> RED Pants Regs LG | I51: 83912164 | J51: 351 | K51: =IFERROR(VLOOKUP(H51,$A$2:$D$99,4,FALSE),0) -> 351 | L51: =J51-K51 -> 0 | M51: =IFERROR(L51=0,"CHECK") -> TRUE
A52: =VLOOKUP(C52,PSR!$F$1:$G$447,2,FALSE) -> RED Pants Regs SM | B52: PAMPERS PANTS DL2 SM10SX40 REG KN2PUGSIN | C52: 83918759 | D52: =SUMIF(PSR!$G$2:$G$447,Sheet3!A52,PSR!$I$2:$I$447) -> 768 | H52: =VLOOKUP(I52,CHOOSE({1,2},([1]IRA!$D$4:$D$285),[1]IRA!$C$4:$C$285),2,FALSE) -> RED Pants Regs NB | I52: 83918758 | J52: 99 | K52: =IFERROR(VLOOKUP(H52,$A$2:$D$99,4,FALSE),0) -> 99 | L52: =J52-K52 -> 0 | M52: =IFERROR(L52=0,"CHECK") -> TRUE
A53: =VLOOKUP(C53,PSR!$F$1:$G$447,2,FALSE) -> RED Pants Regs XL | B53: PAMPERS PANTS DL2 XL6SX40 REG KN GS IN | C53: 80895517 | D53: =SUMIF(PSR!$G$2:$G$447,Sheet3!A53,PSR!$I$2:$I$447) -> 186 | H53: =VLOOKUP(I53,CHOOSE({1,2},([1]IRA!$D$4:$D$285),[1]IRA!$C$4:$C$285),2,FALSE) -> RED Pants Regs SM | I53: 83918759 | J53: 768 | K53: =IFERROR(VLOOKUP(H53,$A$2:$D$99,4,FALSE),0) -> 768 | L53: =J53-K53 -> 0 | M53: =IFERROR(L53=0,"CHECK") -> TRUE
A54: =VLOOKUP(C54,PSR!$F$1:$G$447,2,FALSE) -> BLUE Pants Regs NB | B54: PAMPERS PANTS HL5 XS8SX40 REG GS IN | C54: 80895500 | D54: =SUMIF(PSR!$G$2:$G$447,Sheet3!A54,PSR!$I$2:$I$447) -> 21 | H54: =VLOOKUP(I54,CHOOSE({1,2},([1]IRA!$D$4:$D$285),[1]IRA!$C$4:$C$285),2,FALSE) -> RED Pants Regs XL | I54: 80895517 | J54: 186 | K54: =IFERROR(VLOOKUP(H54,$A$2:$D$99,4,FALSE),0) -> 186 | L54: =J54-K54 -> 0 | M54: =IFERROR(L54=0,"CHECK") -> TRUE
A55: =VLOOKUP(C55,PSR!$F$1:$G$447,2,FALSE) -> BLUE Pants Regs SM | B55: PAMPERS PANTS HL5 SM7SX40 REG GS SO IN | C55: 83912172 | D55: =SUMIF(PSR!$G$2:$G$447,Sheet3!A55,PSR!$I$2:$I$447) -> 159 | H55: =VLOOKUP(I55,CHOOSE({1,2},([1]IRA!$D$4:$D$285),[1]IRA!$C$4:$C$285),2,FALSE) -> RED Pants Jumbo New SM | I55: 83918765 | J55: 1206 | K55: =IFERROR(VLOOKUP(H55,$A$2:$D$99,4,FALSE),0) -> 1206 | L55: =J55-K55 -> 0 | M55: =IFERROR(L55=0,"CHECK") -> TRUE
A56: =VLOOKUP(C56,PSR!$F$1:$G$447,2,FALSE) -> PC Pants LG Econ Pk | B56: PAMPERS DPR MML3.0 LG16SX18 ECON DC IN | C56: 83921920 | D56: =SUMIF(PSR!$G$2:$G$447,Sheet3!A56,PSR!$I$2:$I$447) -> 28 | H56: =VLOOKUP(I56,CHOOSE({1,2},([1]IRA!$D$4:$D$285),[1]IRA!$C$4:$C$285),2,FALSE) -> RED Pants Regs MD | I56: 83912166 | J56: 327 | K56: =IFERROR(VLOOKUP(H56,$A$2:$D$99,4,FALSE),0) -> 327 | L56: =J56-K56 -> 0 | M56: =IFERROR(L56=0,"CHECK") -> TRUE
H57: =VLOOKUP(I57,CHOOSE({1,2},([1]IRA!$D$4:$D$285),[1]IRA!$C$4:$C$285),2,FALSE) -> Active Baby NB Econ | I57: 83933413 | J57: 252 | K57: =IFERROR(VLOOKUP(H57,$A$2:$D$99,4,FALSE),0) -> 252 | L57: =J57-K57 -> 0 | M57: =IFERROR(L57=0,"CHECK") -> TRUE
A58: =VLOOKUP(C58,PSR!$F$1:$G$447,2,FALSE) -> PC Pants NB Econ Pk | B58: PAMPERS DPR MML3.0 XS30SX18 ECON DC IN | C58: 83921924 | D58: =SUMIF(PSR!$G$2:$G$447,Sheet3!A58,PSR!$I$2:$I$447) -> 171 | H58: =VLOOKUP(I58,CHOOSE({1,2},([1]IRA!$D$4:$D$285),[1]IRA!$C$4:$C$285),2,FALSE) -> Pntn HFC 90ml | I58: 80879273 | J58: 120 | K58: =IFERROR(VLOOKUP(H58,$A$2:$D$99,4,FALSE),0) -> 120 | L58: =J58-K58 -> 0 | M58: =IFERROR(L58=0,"CHECK") -> TRUE
A59: =VLOOKUP(C59,PSR!$F$1:$G$447,2,FALSE) -> PC Pants SM Econ Pk | B59: PAMPERS DPR MML3.0 SM26SX18 ECON DC IN | C59: 83921923 | D59: =SUMIF(PSR!$G$2:$G$447,Sheet3!A59,PSR!$I$2:$I$447) -> 75 | H59: =VLOOKUP(I59,CHOOSE({1,2},([1]IRA!$D$4:$D$285),[1]IRA!$C$4:$C$285),2,FALSE) -> PNTN LC 90ML | I59: 80879269 | J59: 24 | K59: =IFERROR(VLOOKUP(H59,$A$2:$D$99,4,FALSE),0) -> 24 | L59: =J59-K59 -> 0 | M59: =IFERROR(L59=0,"CHECK") -> TRUE
A60: =VLOOKUP(C60,PSR!$F$1:$G$447,2,FALSE) -> PC Pants XL Econ PK | B60: PAMPERS DPR MML2.1 XL14SX18 ECON DC IN | C60: 80887692 | D60: =SUMIF(PSR!$G$2:$G$447,Sheet3!A60,PSR!$I$2:$I$447) -> 12 | H60: =VLOOKUP(I60,CHOOSE({1,2},([1]IRA!$D$4:$D$285),[1]IRA!$C$4:$C$285),2,FALSE) -> Pntn SS 90ml | I60: 80879272 | J60: 3 | K60: =IFERROR(VLOOKUP(H60,$A$2:$D$99,4,FALSE),0) -> 3 | L60: =J60-K60 -> 0 | M60: =IFERROR(L60=0,"CHECK") -> TRUE
A61: =VLOOKUP(C61,PSR!$F$1:$G$447,2,FALSE) -> H&S 2in1 SS 72ml | B61: H&S SHM 72MLX48 S&S 2IN1 IN PCR | C61: 83911268 | D61: =SUMIF(PSR!$G$2:$G$447,Sheet3!A61,PSR!$I$2:$I$447) -> 96 | H61: =VLOOKUP(I61,CHOOSE({1,2},([1]IRA!$D$4:$D$285),[1]IRA!$C$4:$C$285),2,FALSE) -> Pntn condi Biotin 3MM 200ml | I61: 80830098 | J61: 1 | K61: =IFERROR(VLOOKUP(H61,$A$2:$D$99,4,FALSE),0) -> 1 | L61: =J61-K61 -> 0 | M61: =IFERROR(L61=0,"CHECK") -> TRUE
A62: =VLOOKUP(C62,PSR!$F$1:$G$447,2,FALSE) -> H&S 7IN1 72ML | B62: H&S SHM 72 ML X 48 7IN1 IN PCR | C62: 83911276 | D62: =SUMIF(PSR!$G$2:$G$447,Sheet3!A62,PSR!$I$2:$I$447) -> 33 | H62: =VLOOKUP(I62,CHOOSE({1,2},([1]IRA!$D$4:$D$285),[1]IRA!$C$4:$C$285),2,FALSE) -> BabyRub 25 ml | I62: 80862572 | J62: 4 | K62: =IFERROR(VLOOKUP(H62,$A$2:$D$99,4,FALSE),0) -> 4 | L62: =J62-K62 -> 0 | M62: =IFERROR(L62=0,"CHECK") -> TRUE
A63: =VLOOKUP(C63,PSR!$F$1:$G$447,2,FALSE) -> H&S AHF 90ML | B63: H&S SHM 72ML X 48 AHF IN PCR | C63: 83911270 | D63: =SUMIF(PSR!$G$2:$G$447,Sheet3!A63,PSR!$I$2:$I$447) -> 231 | H63: =VLOOKUP(I63,CHOOSE({1,2},([1]IRA!$D$4:$D$285),[1]IRA!$C$4:$C$285),2,FALSE) -> Vicks Double Power Standee Pouch 25s Menthol | I63: 80895630 | J63: 6 | K63: =IFERROR(VLOOKUP(H63,$A$2:$D$99,4,FALSE),0) -> 6 | L63: =J63-K63 -> 0 | M63: =IFERROR(L63=0,"CHECK") -> TRUE
A64: =VLOOKUP(C64,PSR!$F$1:$G$447,2,FALSE) -> H&S BG 72ML | B64: H&S SHM 72ML X 48 DEEP CLEANSE IN PCR | C64: 83911281 | D64: =SUMIF(PSR!$G$2:$G$447,Sheet3!A64,PSR!$I$2:$I$447) -> 123 | H64: =VLOOKUP(I64,CHOOSE({1,2},([1]IRA!$D$4:$D$285),[1]IRA!$C$4:$C$285),2,FALSE) -> ZZZQUIL 10S | I64: 80870946 | J64: 1 | K64: =IFERROR(VLOOKUP(H64,$A$2:$D$99,4,FALSE),0) -> 1 | L64: =J64-K64 -> 0 | M64: =IFERROR(L64=0,"CHECK") -> TRUE
A65: =VLOOKUP(C65,PSR!$F$1:$G$447,2,FALSE) -> H&S CM 90ML | B65: H&S SHM 72 ML X 48 CM IN EDTA | C65: 80892904 | D65: =SUMIF(PSR!$G$2:$G$447,Sheet3!A65,PSR!$I$2:$I$447) -> 414 | H65: =VLOOKUP(I65,CHOOSE({1,2},([1]IRA!$D$4:$D$285),[1]IRA!$C$4:$C$285),2,FALSE) -> Whspr ON Koala Pants L-XL 6s | I65: 80870358 | J65: 81 | K65: =IFERROR(VLOOKUP(H65,$A$2:$D$99,4,FALSE),0) -> 81 | L65: =J65-K65 -> 0 | M65: =IFERROR(L65=0,"CHECK") -> TRUE
A66: =VLOOKUP(C66,PSR!$F$1:$G$447,2,FALSE) -> H&S SS 90ML | B66: H&S SHM 72ML X 48 S&S IN PCR | C66: 83911280 | D66: =SUMIF(PSR!$G$2:$G$447,Sheet3!A66,PSR!$I$2:$I$447) -> 171 | H66: =VLOOKUP(I66,CHOOSE({1,2},([1]IRA!$D$4:$D$285),[1]IRA!$C$4:$C$285),2,FALSE) -> whspr Choice ON XXL 6s | I66: 80869896 | J66: 450 | K66: =IFERROR(VLOOKUP(H66,$A$2:$D$99,4,FALSE),0) -> 450 | L66: =J66-K66 -> 0 | M66: =IFERROR(L66=0,"CHECK") -> TRUE
A67: =VLOOKUP(C67,PSR!$F$1:$G$447,2,FALSE) -> PNTN LC 90ML | B67: PNTN SHM 90MLX48 HS LC IN GST | C67: 80879269 | D67: =SUMIF(PSR!$G$2:$G$447,Sheet3!A67,PSR!$I$2:$I$447) -> 24 | H67: =VLOOKUP(I67,CHOOSE({1,2},([1]IRA!$D$4:$D$285),[1]IRA!$C$4:$C$285),2,FALSE) -> whspr Choice Ultra 6s | I67: 83911635 | J67: 2584 | K67: =IFERROR(VLOOKUP(H67,$A$2:$D$99,4,FALSE),0) -> 2584 | L67: =J67-K67 -> 0 | M67: =IFERROR(L67=0,"CHECK") -> TRUE
A68: =VLOOKUP(C68,PSR!$F$1:$G$447,2,FALSE) -> Pntn HFC 90ml | B68: PNTN SHM 75 MLX48 HS HFC IN GST | C68: 80879273 | D68: =SUMIF(PSR!$G$2:$G$447,Sheet3!A68,PSR!$I$2:$I$447) -> 120 | H68: =VLOOKUP(I68,CHOOSE({1,2},([1]IRA!$D$4:$D$285),[1]IRA!$C$4:$C$285),2,FALSE) -> whspr Choice Wings 6s | I68: 83911777 | J68: 204 | K68: =IFERROR(VLOOKUP(H68,$A$2:$D$99,4,FALSE),0) -> 220 | L68: =J68-K68 -> -16 | M68: =IFERROR(L68=0,"CHECK") -> FALSE
A69: =VLOOKUP(C69,PSR!$F$1:$G$447,2,FALSE) -> PNTN CONDI BOND REPAIR 200ML | B69: PTN ROT 180MLX24 BR D50H199 GOLDIE IN | C69: 80876990 | D69: =SUMIF(PSR!$G$2:$G$447,Sheet3!A69,PSR!$I$2:$I$447) -> 2 | H69: =VLOOKUP(I69,CHOOSE({1,2},([1]IRA!$D$4:$D$285),[1]IRA!$C$4:$C$285),2,FALSE) -> whspr Choice XL 6s | I69: 83911783 | J69: 200 | K69: =IFERROR(VLOOKUP(H69,$A$2:$D$99,4,FALSE),0) -> 200 | L69: =J69-K69 -> 0 | M69: =IFERROR(L69=0,"CHECK") -> TRUE
A70: =VLOOKUP(C70,PSR!$F$1:$G$447,2,FALSE) -> Pntn condi Collagen 3MM 200ml | B70: PNTN 3MM COLLAGEN COND 200MLX24 IN | C70: 80830097 | D70: =SUMIF(PSR!$G$2:$G$447,Sheet3!A70,PSR!$I$2:$I$447) -> 5 | H70: whspr Maxi Rg 15s | I70: 80869511 | J70: 11 | K70: =IFERROR(VLOOKUP(H70,$A$2:$D$99,4,FALSE),0) -> 11 | L70: =J70-K70 -> 0 | M70: =IFERROR(L70=0,"CHECK") -> TRUE
A71: =VLOOKUP(C71,PSR!$F$1:$G$447,2,FALSE) -> Olay NA IGF 20gm | B71: OLAY NA IGF 20GX6X8 IN_RS109 PU | C71: 80878182 | D71: =SUMIF(PSR!$G$2:$G$447,Sheet3!A71,PSR!$I$2:$I$447) -> 42 | H71: =VLOOKUP(I71,CHOOSE({1,2},([1]IRA!$D$4:$D$285),[1]IRA!$C$4:$C$285),2,FALSE) -> whspr Liners 20s | I71: 80870015 | J71: 3 | K71: =IFERROR(VLOOKUP(H71,$A$2:$D$99,4,FALSE),0) -> 3 | L71: =J71-K71 -> 0 | M71: =IFERROR(L71=0,"CHECK") -> TRUE
A72: =VLOOKUP(C72,PSR!$F$1:$G$447,2,FALSE) -> Fusion Power Raz | B72: Fusion Pow Rzr 557.1 1UP 1X6X6IT 575 INR | C72: 80797472 | D72: =SUMIF(PSR!$G$2:$G$447,Sheet3!A72,PSR!$I$2:$I$447) -> 1 | H72: =VLOOKUP(I72,CHOOSE({1,2},([1]IRA!$D$4:$D$285),[1]IRA!$C$4:$C$285),2,FALSE) -> Whspr ON Koala Pants M-L 6s | I72: 80870357 | J72: 178 | K72: =IFERROR(VLOOKUP(H72,$A$2:$D$99,4,FALSE),0) -> 178 | L72: =J72-K72 -> 0 | M72: =IFERROR(L72=0,"CHECK") -> TRUE
A73: =VLOOKUP(C73,PSR!$F$1:$G$447,2,FALSE) -> Fusion Raz | B73: Fusion Razor 557.1 1UP 1X6X6IT 425 INR | C73: 80797470 | D73: =SUMIF(PSR!$G$2:$G$447,Sheet3!A73,PSR!$I$2:$I$447) -> 3 | H73: =VLOOKUP(I73,CHOOSE({1,2},([1]IRA!$D$4:$D$285),[1]IRA!$C$4:$C$285),2,FALSE) -> whspr Ult ON XXL 7s | I73: 83916746 | J73: 57 | K73: =IFERROR(VLOOKUP(H73,$A$2:$D$99,4,FALSE),0) -> 57 | L73: =J73-K73 -> 0 | M73: =IFERROR(L73=0,"CHECK") -> TRUE
A74: =VLOOKUP(C74,PSR!$F$1:$G$447,2,FALSE) -> Turbo Mach-3 Rzr Flexi | B74: MACH3 TRB FLEXI RAZ1UP F1 1X6X6 399 INR | C74: 80803712 | D74: =SUMIF(PSR!$G$2:$G$447,Sheet3!A74,PSR!$I$2:$I$447) -> 2 | H74: =VLOOKUP(I74,CHOOSE({1,2},([1]IRA!$D$4:$D$285),[1]IRA!$C$4:$C$285),2,FALSE) -> whspr Ult XXXL ON 4s | I74: 80887674 | J74: 24 | K74: =IFERROR(VLOOKUP(H74,$A$2:$D$99,4,FALSE),0) -> 24 | L74: =J74-K74 -> 0 | M74: =IFERROR(L74=0,"CHECK") -> TRUE
A75: =VLOOKUP(C75,PSR!$F$1:$G$447,2,FALSE) -> Vector3 Cart 4s | B75: VEC3 CRT 4 PSHBT 4X12X6 INR275 | C75: 80818346 | D75: =SUMIF(PSR!$G$2:$G$447,Sheet3!A75,PSR!$I$2:$I$447) -> 3 | H75: =VLOOKUP(I75,CHOOSE({1,2},([1]IRA!$D$4:$D$285),[1]IRA!$C$4:$C$285),2,FALSE) -> Whspr Soft XL 6s | I75: 83914233 | J75: 18 | K75: =IFERROR(VLOOKUP(H75,$A$2:$D$99,4,FALSE),0) -> 18 | L75: =J75-K75 -> 0 | M75: =IFERROR(L75=0,"CHECK") -> TRUE
A76: =VLOOKUP(C76,PSR!$F$1:$G$447,2,FALSE) -> OB Crisscross Antiplaq Neem B2G2 Sft | B76: OB OM196 CRCS DeepClnNEEM40S 160INR4X6X6__ | C76: 80895783 | D76: =SUMIF(PSR!$G$2:$G$447,Sheet3!A76,PSR!$I$2:$I$447) -> 4 | H76: =VLOOKUP(I76,CHOOSE({1,2},([1]IRA!$D$4:$D$285),[1]IRA!$C$4:$C$285),2,FALSE) -> whspr Ultra XL+ 7s CFC | I76: 80893410 | J76: 99 | K76: =IFERROR(VLOOKUP(H76,$A$2:$D$99,4,FALSE),0) -> 99 | L76: =J76-K76 -> 0 | M76: =IFERROR(L76=0,"CHECK") -> TRUE
A77: =VLOOKUP(C77,PSR!$F$1:$G$447,2,FALSE) -> OB Crisscross Bact Blast B2G1 Sft | B77: OB CRCSDEPCLNBACBST40S 170INR B2G1 3X6X8 | C77: 80894418 | D77: =SUMIF(PSR!$G$2:$G$447,Sheet3!A77,PSR!$I$2:$I$447) -> 2 | H77: =VLOOKUP(I77,CHOOSE({1,2},([1]IRA!$D$4:$D$285),[1]IRA!$C$4:$C$285),2,FALSE) -> Foam (Charcoal) 200ml | I77: 80866728 | J77: 5 | K77: =IFERROR(VLOOKUP(H77,$A$2:$D$99,4,FALSE),0) -> 5 | L77: =J77-K77 -> 0 | M77: =IFERROR(L77=0,"CHECK") -> TRUE
A78: =VLOOKUP(C78,PSR!$F$1:$G$447,2,FALSE) -> OB Crisscross Rs50 3s | B78: OB OM196 PH CRCR 40S BCD 108INR 3X6X8 | C78: 80894404 | D78: =SUMIF(PSR!$G$2:$G$447,Sheet3!A78,PSR!$I$2:$I$447) -> 2 | H78: =VLOOKUP(I78,CHOOSE({1,2},([1]IRA!$D$4:$D$285),[1]IRA!$C$4:$C$285),2,FALSE) -> Foam (Lmn) 200ml | I78: 80866725 | J78: 5 | K78: =IFERROR(VLOOKUP(H78,$A$2:$D$99,4,FALSE),0) -> 5 | L78: =J78-K78 -> 0 | M78: =IFERROR(L78=0,"CHECK") -> TRUE
A79: =VLOOKUP(C79,PSR!$F$1:$G$447,2,FALSE) -> OB KIDS CHOTA BHEEM 3S | B79: OB OK006 EMKB LITE 3CT BCD 60INR 3X6X8__ | C79: 80895602 | D79: =SUMIF(PSR!$G$2:$G$447,Sheet3!A79,PSR!$I$2:$I$447) -> 16 | H79: =VLOOKUP(I79,CHOOSE({1,2},([1]IRA!$D$4:$D$285),[1]IRA!$C$4:$C$285),2,FALSE) -> Vector3 Rzr | I79: 80818341 | J79: 5 | K79: =IFERROR(VLOOKUP(H79,$A$2:$D$99,4,FALSE),0) -> 5 | L79: =J79-K79 -> 0 | M79: =IFERROR(L79=0,"CHECK") -> TRUE
A80: =VLOOKUP(C80,PSR!$F$1:$G$447,2,FALSE) -> Foam (Mnth) 200ml | B80: GIL FM SHVP 196 G MNTH 1X24 INR 270 | C80: 80866727 | D80: =SUMIF(PSR!$G$2:$G$447,Sheet3!A80,PSR!$I$2:$I$447) -> 1 | H80: =VLOOKUP(I80,CHOOSE({1,2},([1]IRA!$D$4:$D$285),[1]IRA!$C$4:$C$285),2,FALSE) -> ATOM ORIGINAL 150ML | I80: 80830411 | J80: 6 | K80: =IFERROR(VLOOKUP(H80,$A$2:$D$99,4,FALSE),0) -> 6 | L80: =J80-K80 -> 0 | M80: =IFERROR(L80=0,"CHECK") -> TRUE
A81: =VLOOKUP(C81,PSR!$F$1:$G$447,2,FALSE) -> Foam (Reg) 200ml | B81: GIL FM SHVP 196G REG 1X24 INR 249 | C81: 80866724 | D81: =SUMIF(PSR!$G$2:$G$447,Sheet3!A81,PSR!$I$2:$I$447) -> 1 | H81: =VLOOKUP(I81,CHOOSE({1,2},([1]IRA!$D$4:$D$285),[1]IRA!$C$4:$C$285),2,FALSE) -> OB CAPH Power brush Sft | I81: 80843635 | J81: 1 | K81: =IFERROR(VLOOKUP(H81,$A$2:$D$99,4,FALSE),0) -> 1 | L81: =J81-K81 -> 0 | M81: =IFERROR(L81=0,"CHECK") -> TRUE
A82: =VLOOKUP(C82,PSR!$F$1:$G$447,2,FALSE) -> Cream GIL Lime 93gm | B82: GIL LIME SHV CRM 70G 1X96 80INR | C82: 80862826 | D82: =SUMIF(PSR!$G$2:$G$447,Sheet3!A82,PSR!$I$2:$I$447) -> 6 | H82: =VLOOKUP(I82,CHOOSE({1,2},([1]IRA!$D$4:$D$285),[1]IRA!$C$4:$C$285),2,FALSE) -> PNTN CONDI BOND REPAIR 200ML | I82: 80876990 | J82: 2 | K82: =IFERROR(VLOOKUP(H82,$A$2:$D$99,4,FALSE),0) -> 2 | L82: =J82-K82 -> 0 | M82: =IFERROR(L82=0,"CHECK") -> TRUE
... A99: =VLOOKUP(C99,PSR!$F$1:$G$447,2,FALSE) -> Pntn condi Biotin 3MM 200ml | B99: PNTN 3MM BIOTIN COND 200MLX24 IN | C99: 80830098 | D99: =SUMIF(PSR!$G$2:$G$447,Sheet3!A99,PSR!$I$2:$I$447) -> 1 | H99: =VLOOKUP(I99,CHOOSE({1,2},([1]IRA!$D$4:$D$285),[1]IRA!$C$4:$C$285),2,FALSE) -> BLUE Pants Regs LG | I99: 80895503 | J99: 6 | K99: =IFERROR(VLOOKUP(H99,$A$2:$D$99,4,FALSE),0) -> 6 | L99: =J99-K99 -> 0 | M99: =IFERROR(L99=0,"CHECK") -> TRUE
H100: =VLOOKUP(I100,CHOOSE({1,2},([1]IRA!$D$4:$D$285),[1]IRA!$C$4:$C$285),2,FALSE) -> Inhaler Keychain | I100: 80885888 | J100: 9 | K100: =IFERROR(VLOOKUP(H100,$A$2:$D$99,4,FALSE),0) -> 9 | L100: =J100-K100 -> 0 | M100: =IFERROR(L100=0,"CHECK") -> TRUE

Sheet Sheet4
A1: 80862826 | B1: 3*Cream GIL Lime 93gm | C1: 3 | D1: 190.2 | I1: =C1-H1 -> 3 | M1: 80862826 | N1: =SUMIF($A$1:$A$453,M1,$I$1:$I$453) -> 6
A2: 80865298 | B2: Gillette Aftershave Refreshing Breeze 50ml | C2: 1 | D2: 258.04 | I2: =C2-H2 -> 1 | M2: 80865298 | N2: =SUMIF($A$1:$A$453,M2,$I$1:$I$453) -> 2
A3: 83904003 | B3: Gillette Cartridges ( 16 Cartridges) | C3: 80 | D3: 8816 | E3: 4CANCEL | G3: 1 | H3: 4 | I3: =C3-H3 -> 76 | M3: 83904003 | N3: =SUMIF($A$1:$A$453,M3,$I$1:$I$453) -> 152
A4: 80866726 | B4: Gillette Classic Regular Foam - 150g (50g x 3) | C4: 9 | D4: 763.47 | I4: =C4-H4 -> 9 | M4: 80866726 | N4: =SUMIF($A$1:$A$453,M4,$I$1:$I$453) -> 18
A5: 80797472 | B5: Gillette Fusion Power Razor | C5: 1 | D5: 513.39 | I5: =C5-H5 -> 1 | M5: 80797472 | N5: =SUMIF($A$1:$A$453,M5,$I$1:$I$453) -> 1
A6: 80797470 | B6: Gillette Fusion Razor | C6: 1 | D6: 379.46 | I6: =C6-H6 -> 1 | M6: 80797470 | N6: =SUMIF($A$1:$A$453,M6,$I$1:$I$453) -> 3
A7: 80867316 | B7: Gillette Guard 3-in-1 Blade Cartridge - 4 cartridge (2 x 2) | C7: 8 | D7: 707.12 | I7: =C7-H7 -> 8 | M7: 80867316 | N7: =SUMIF($A$1:$A$453,M7,$I$1:$I$453) -> 18
A8: 80896468 | B8: Gillette Guard Shaving Cream - 375gm (125gm x 3) | C8: 30 | D8: 1488 | I8: =C8-H8 -> 30 | M8: 80896468 | N8: =SUMIF($A$1:$A$453,M8,$I$1:$I$453) -> 60
A9: 80876082 | B9: Gillette Mach3 Cartridge 2s | C9: 7 | D9: 2181.2 | I9: =C9-H9 -> 7 | M9: 80876082 | N9: =SUMIF($A$1:$A$453,M9,$I$1:$I$453) -> 14
A10: 80803710 | B10: Gillette Mach3 Charcoal Razor | C10: 1 | D10: 311.6 | I10: =C10-H10 -> 1 | M10: 80803710 | N10: =SUMIF($A$1:$A$453,M10,$I$1:$I$453) -> 4
A11: 80862828 | B11: Gillette Regular Shaving Cream for Men - 279g (93g x 3) | C11: 3 | D11: 190.2 | I11: =C11-H11 -> 3 | M11: 80862828 | N11: =SUMIF($A$1:$A$453,M11,$I$1:$I$453) -> 9
A12: 80753181 | B12: Gillette Sensitive Aloe Shaving Gel for Men - 180g (60g x 3) | C12: 3 | D12: 265.17 | I12: =C12-H12 -> 3 | M12: 80753181 | N12: =SUMIF($A$1:$A$453,M12,$I$1:$I$453) -> 3
A13: 80866724 | B13: Gillette Shaving Foam Classic Regular 196g | C13: 1 | D13: 222.32 | I13: =C13-H13 -> 1 | M13: 80866724 | N13: =SUMIF($A$1:$A$453,M13,$I$1:$I$453) -> 1
A14: 80866723 | B14: Gillette Shaving Foam Classic Sensitive 418g | C14: 34 | D14: 8803.28 | I14: =C14-H14 -> 34 | M14: 80866723 | N14: =SUMIF($A$1:$A$453,M14,$I$1:$I$453) -> 158
A15: 80866729 | B15: Gillette Shaving Foam Classis Regular 418g | C15: 42 | D15: 10874.64 | I15: =C15-H15 -> 42 | M15: 80866729 | N15: =SUMIF($A$1:$A$453,M15,$I$1:$I$453) -> 284
A16: 80875507 | B16: Gillette Vector Razor - Pack of 2 | C16: 10 | D16: 937.4 | E16: 2CANCEL | G16: 1 | H16: 2 | I16: =C16-H16 -> 8 | M16: 80875507 | N16: =SUMIF($A$1:$A$453,M16,$I$1:$I$453) -> 14
A17: 80864300 | B17: Gillette Vector Razor Cartridges - 4 pc (2 x 2) | C17: 26 | D17: 2250.3 | I17: =C17-H17 -> 26 | M17: 80864300 | N17: =SUMIF($A$1:$A$453,M17,$I$1:$I$453) -> 58
A18: 80875513 | B18: Gillette Venus Bikini Sensitive Razor | C18: 13 | D18: 1995.5 | I18: =C18-H18 -> 13 | M18: 80875513 | N18: =SUMIF($A$1:$A$453,M18,$I$1:$I$453) -> 56
A19: 80840354 | B19: Gillette Venus Comfortglide Razor 1 Pc | C19: 25 | D19: 8223.75 | G19: 2 | H19: 2 | I19: =C19-H19 -> 23 | M19: 80840354 | N19: =SUMIF($A$1:$A$453,M19,$I$1:$I$453) -> 50
A20: 80840352 | B20: Gillette Venus ComfortGlide Cartridges (2 pieces) | C20: 17 | D20: 7083.39 | I20: =C20-H20 -> 17 | M20: 80840352 | N20: =SUMIF($A$1:$A$453,M20,$I$1:$I$453) -> 25
A21: 80864296 | B21: Gillette Venus Simply Razor - 3 Razors (1 x 3) | C21: 6 | D21: 521.1 | I21: =C21-H21 -> 6 | M21: 80864296 | N21: =SUMIF($A$1:$A$453,M21,$I$1:$I$453) -> 24
A22: 80864297 | B22: Gillette Venus Skin Love Razor - Pack of 1 | C22: 249 | D22: 38221.5 | E22: 3CANCEL | G22: 7 | H22: 7 | I22: =C22-H22 -> 242 | M22: 80864297 | N22: =SUMIF($A$1:$A$453,M22,$I$1:$I$453) -> 629
A23: 80832389 | B23: Gillette Venus Smooth Sensitive Cartridges (2 pieces) | C23: 1 | D23: 328.95 | G23: 1 | H23: 1 | I23: =C23-H23 -> 0 | M23: 80832389 | N23: =SUMIF($A$1:$A$453,M23,$I$1:$I$453) -> 8
A24: 80832398 | B24: Gillette Venus Smooth Sensitive Razor 1 Pc | C24: 10 | D24: 2850.9 | E24: 1CANCEL | G24: 1 | H24: 1 | I24: =C24-H24 -> 9 | M24: 80832398 | N24: =SUMIF($A$1:$A$453,M24,$I$1:$I$453) -> 30
A25: 80832394 | B25: Gillette Venus Snap Razor, Pack of 1 | C25: 3 | D25: 1118.4 | I25: =C25-H25 -> 3 | M25: 80832394 | N25: =SUMIF($A$1:$A$453,M25,$I$1:$I$453) -> 13
A26: 83911270 | B26: H&S AHF Anti-Dandruff Shampoo (72 ml), Pack of 3 | C26: 135 | D26: 9694.35 | G26: 2 | H26: 6 | I26: =C26-H26 -> 129 | M26: 83911270 | N26: =SUMIF($A$1:$A$453,M26,$I$1:$I$453) -> 231
A27: 80892904 | B27: H&S CM Shampoo (72 ml), Pack of 3 | C27: 219 | D27: 15726.39 | E27: 3CANCEL | G27: 3 | H27: 9 | I27: =C27-H27 -> 210 | M27: 80892904 | N27: =SUMIF($A$1:$A$453,M27,$I$1:$I$453) -> 414
A28: 83911280 | B28: H&S S&S Shampoo (72 ml), Pack of 3 | C28: 111 | D28: 7970.91 | G28: 1 | H28: 3 | I28: =C28-H28 -> 108 | M28: 83911280 | N28: =SUMIF($A$1:$A$453,M28,$I$1:$I$453) -> 171
A29: 80880909 | B29: H&S S&S 2-in-1 Shampoo + Conditioner 72 ml, Pack of 3 | C29: 63 | D29: 4868.01 | I29: =C29-H29 -> 63 | M29: 80880909 | N29: =SUMIF($A$1:$A$453,M29,$I$1:$I$453) -> 87
A30: 83911276 | B30: Head & Shoulders 7in1 Shampoo | 7 benefits , Pack of 3 | C30: 12 | D30: 861.72 | I30: =C30-H30 -> 12 | M30: 83911276 | N30: =SUMIF($A$1:$A$453,M30,$I$1:$I$453) -> 33
A31: 83911281 | B31: Head & Shoulders Deep Cleanse for Oily Scalp |, Pack of 3 | C31: 39 | D31: 2800.59 | G31: 1 | H31: 3 | I31: =C31-H31 -> 36 | M31: 83911281 | N31: =SUMIF($A$1:$A$453,M31,$I$1:$I$453) -> 123
A32: 80894418 | B32: OB CRCSDEPCLNBACBST40S 170INR B2G1 3X6X8 | C32: 2 | D32: 141.67 | I32: =C32-H32 -> 2 | M32: 80894418 | N32: =SUMIF($A$1:$A$453,M32,$I$1:$I$453) -> 2
A33: 80878182 | B33: Olay Natural Aura Radiance Cream - 40g (20g x 2) | C33: 20 | D33: 1895.6 | I33: =C33-H33 -> 20 | M33: 80878182 | N33: =SUMIF($A$1:$A$453,M33,$I$1:$I$453) -> 42
A34: 80762958 | B34: Old Spice Lionpride No Gas Deodorant , Pack of 2 (17ml x 2) | C34: 1 | D34: 107.14 | I34: =C34-H34 -> 1 | M34: 80762958 | N34: =SUMIF($A$1:$A$453,M34,$I$1:$I$453) -> 1
A35: 80895603 | B35: Oral-B Cavity Defense Neem Soft - 8 brush (4 x 2) | C35: 2 | D35: 176.68 | I35: =C35-H35 -> 2 | M35: 80895603 | N35: =SUMIF($A$1:$A$453,M35,$I$1:$I$453) -> 6
A36: 80895602 | B36: Oral-B Chhota Bheem Kids Extra Soft , 6 brush (3 x 2) | C36: 2 | D36: 83.34 | I36: =C36-H36 -> 2 | M36: 80895602 | N36: =SUMIF($A$1:$A$453,M36,$I$1:$I$453) -> 16
A37: 80895783 | B37: Oral-B Criss Cross Anti-Plaque Neem- 8 brush (4 x 2) | C37: 4 | D37: 466.68 | I37: =C37-H37 -> 4 | M37: 80895783 | N37: =SUMIF($A$1:$A$453,M37,$I$1:$I$453) -> 4
A38: 80895465 | B38: Pampers Baby Diaper Pants- 4 to 8 kg (Small, 22) | C38: 19 | D38: 6179.18 | E38: 1CANCEL | G38: 1 | H38: 1 | I38: =C38-H38 -> 18 | M38: 80895465 | N38: =SUMIF($A$1:$A$453,M38,$I$1:$I$453) -> 29
A39: 83921920 | B39: Pampers Diapers L 16pcs Premium Care Pants | C39: 15 | D39: 4375.05 | I39: =C39-H39 -> 15 | M39: 83921920 | N39: =SUMIF($A$1:$A$453,M39,$I$1:$I$453) -> 28
A40: 80887983 | B40: Pampers Diapers L 42pcs Happy Skin Pants | C40: 2 | D40: 933.34 | I40: =C40-H40 -> 2 | M40: 80887983 | N40: =SUMIF($A$1:$A$453,M40,$I$1:$I$453) -> 6
A41: 83921921 | B41: Pampers Diapers M 20pcs Premium Care Pants | C41: 32 | D41: 9333.44 | E41: 1CANCEL | G41: 1 | H41: 1 | I41: =C41-H41 -> 31 | M41: 83921921 | N41: =SUMIF($A$1:$A$453,M41,$I$1:$I$453) -> 115
A42: 83918762 | B42: Pampers Diapers M 48pcs Happy Skin Pants | C42: 5 | D42: 2537.5 | I42: =C42-H42 -> 5 | M42: 83918762 | N42: =SUMIF($A$1:$A$453,M42,$I$1:$I$453) -> 90
A43: 83921924 | B43: Pampers Diapers New born 30pcs Premium Care | C43: 83 | D43: 24208.61 | E43: 1CANCEL | G43: 1 | H43: 1 | I43: =C43-H43 -> 82 | M43: 83921924 | N43: =SUMIF($A$1:$A$453,M43,$I$1:$I$453) -> 171
A44: 83921923 | B44: Pampers Diapers S 26pcs Premium Care Pants | C44: 19 | D44: 5541.73 | I44: =C44-H44 -> 19 | M44: 83921923 | N44: =SUMIF($A$1:$A$453,M44,$I$1:$I$453) -> 75
A45: 80887692 | B45: Pampers Diapers XL 14pcs Premium Care Pants | C45: 4 | D45: 1217.36 | I45: =C45-H45 -> 4 | M45: 80887692 | N45: =SUMIF($A$1:$A$453,M45,$I$1:$I$453) -> 12
A46: 80895502 | B46: Pampers Happy Skin Pant (MD) - 18 diapers (6 x 3) | C46: 3 | D46: 245.01 | I46: =C46-H46 -> 3 | M46: 80895502 | N46: =SUMIF($A$1:$A$453,M46,$I$1:$I$453) -> 6
A47: 80895500 | B47: Pampers Happy Skin Pant (NB) - 24 diapers (8 x 3) | C47: 12 | D47: 930 | I47: =C47-H47 -> 12 | M47: 80895500 | N47: =SUMIF($A$1:$A$453,M47,$I$1:$I$453) -> 21
A48: 83912172 | B48: Pampers Happy Skin Pant (SM) - 21 diapers (7 x 3) | C48: 69 | D48: 5347.5 | I48: =C48-H48 -> 69 | M48: 83912172 | N48: =SUMIF($A$1:$A$453,M48,$I$1:$I$453) -> 159
A49: 80895504 | B49: Pampers Happy Skin Pant , XL - 14 diapers (7 x 2) | C49: 8 | D49: 993.36 | I49: =C49-H49 -> 8 | M49: 80895504 | N49: =SUMIF($A$1:$A$453,M49,$I$1:$I$453) -> 10
A50: 83912164 | B50: Pampers Happy Sleep Pant (L) - (7 x 3) 21 diapers | C50: 135 | D50: 11025.45 | E50: 3CANCEL | G50: 1 | H50: 3 | I50: =C50-H50 -> 132 | M50: 83912164 | N50: =SUMIF($A$1:$A$453,M50,$I$1:$I$453) -> 351
A51: 83918758 | B51: Pampers Happy Sleep Pant (NB) - 30 pc (10 x 3) | C51: 33 | D51: 2612.61 | I51: =C51-H51 -> 33 | M51: 83918758 | N51: =SUMIF($A$1:$A$453,M51,$I$1:$I$453) -> 99
A52: 83918759 | B52: Pampers Happy Sleep Pant (SM) - (10 x 3) 30 diapers | C52: 237 | D52: 18763.29 | I52: =C52-H52 -> 237 | M52: 83918759 | N52: =SUMIF($A$1:$A$453,M52,$I$1:$I$453) -> 768
A53: 80895517 | B53: Pampers Happy Sleep Pant , XL - 18 diapers (6 x 3) | C53: 66 | D53: 6435 | I53: =C53-H53 -> 66 | M53: 80895517 | N53: =SUMIF($A$1:$A$453,M53,$I$1:$I$453) -> 186
A54: 83918765 | B54: Pampers Happy Sleep Pant Baby Diapers,(S), 60 | C54: 549 | D54: 278617.5 | E54: 3CANCEL | G54: 4 | H54: 4 | I54: =C54-H54 -> 545 | M54: 83918765 | N54: =SUMIF($A$1:$A$453,M54,$I$1:$I$453) -> 1206
A55: 83912166 | B55: Pampers Happy Sleep Pant(MD) - (8 x 3) 24 diapers | C55: 147 | D55: 12005.49 | E55: 3CANCEL | G55: 2 | H55: 6 | I55: =C55-H55 -> 141 | M55: 83912166 | N55: =SUMIF($A$1:$A$453,M55,$I$1:$I$453) -> 327
A56: 83933413 | B56: Pampers New born 24pcs Active Baby Taped | C56: 96 | D56: 33308.16 | I56: =C56-H56 -> 96 | M56: 83933413 | N56: =SUMIF($A$1:$A$453,M56,$I$1:$I$453) -> 252
A57: 80879273 | B57: Pantene Advanced Hair Fall Control - 225ml (75ml x 3) | C57: 48 | D57: 3600 | G57: 2 | H57: 6 | I57: =C57-H57 -> 42 | M57: 80879273 | N57: =SUMIF($A$1:$A$453,M57,$I$1:$I$453) -> 120
A58: 80879269 | B58: Pantene Lively Clean Shampoo - 225ml (75ml x 3) | C58: 9 | D58: 613.62 | I58: =C58-H58 -> 9 | M58: 80879269 | N58: =SUMIF($A$1:$A$453,M58,$I$1:$I$453) -> 24
A59: 80879272 | B59: Pantene Silky Smooth Shampoo - 225ml (75ml x 3) | C59: 6 | D59: 409.08 | G59: 1 | H59: 3 | I59: =C59-H59 -> 3 | M59: 80879272 | N59: =SUMIF($A$1:$A$453,M59,$I$1:$I$453) -> 3
A60: 80830098 | B60: PNTN 3MM BIOTIN COND 200MLX24 IN | C60: 1 | D60: 252.17 | I60: =C60-H60 -> 1 | M60: 80830098 | N60: =SUMIF($A$1:$A$453,M60,$I$1:$I$453) -> 1
A61: 80862572 | B61: Vicks BabyRub Soothing Vapor Ointment - 50ml (25ml x 2) | C61: 2 | D61: 195.26 | I61: =C61-H61 -> 2 | M61: 80862572 | N61: =SUMIF($A$1:$A$453,M61,$I$1:$I$453) -> 4
A62: 80895630 | B62: Vicks Double Menthol Cough - 75 units (Pack of 25 x 3) | C62: 3 | D62: 125.16 | I62: =C62-H62 -> 3 | M62: 80895630 | N62: =SUMIF($A$1:$A$453,M62,$I$1:$I$453) -> 6
A63: 80870946 | B63: Vicks ZzzQuil Natura Sleep Gummies Pack of 10 | C63: 1 | D63: 187.75 | I63: =C63-H63 -> 1 | M63: 80870946 | N63: =SUMIF($A$1:$A$453,M63,$I$1:$I$453) -> 1
A64: 80870358 | B64: WHISPER BINDAZZZ NIGHTS , 6 L-XL | C64: 36 | D64: 9091.08 | I64: =C64-H64 -> 36 | M64: 80870358 | N64: =SUMIF($A$1:$A$453,M64,$I$1:$I$453) -> 81
A65: 80869896 | B65: Whisper Choice XXL Sanitary - 18 pads (6 x 3) | C65: 252 | D65: 12486.6 | E65: 6CANCEL | G65: 2 | H65: 6 | I65: =C65-H65 -> 246 | M65: 80869896 | N65: =SUMIF($A$1:$A$453,M65,$I$1:$I$453) -> 450
A66: 83911635 | B66: Whisper Choice Ultra XL Wings Sanitary (Pack of 24) | C66: 1428 | D66: 64317.12 | E66: 4CANCEL | G66: 1 | H66: 4 | I66: =C66-H66 -> 1424 | M66: 83911635 | N66: =SUMIF($A$1:$A$453,M66,$I$1:$I$453) -> 2584
A67: 83911777 | B67: Whisper Choice Wings - 24 pads (6 x 4) | C67: 92 | D67: 3314.76 | G67: 1 | H67: 4 | I67: =C67-H67 -> 88 | M67: 83911777 | N67: =SUMIF($A$1:$A$453,M67,$I$1:$I$453) -> 204
A68: 83911783 | B68: Whisper Choice XL 6pcs (Pack of 4) | C68: 112 | D68: 4540.48 | I68: =C68-H68 -> 112 | M68: 83911783 | N68: =SUMIF($A$1:$A$453,M68,$I$1:$I$453) -> 200
A69: 80869511 | B69: Whisper Maxi Reg 15pcs | C69: 10 | D69: 1981.9 | E69: -2 | G69: 1 | H69: 2 | I69: =C69-H69 -> 8 | M69: 80869511 | N69: =SUMIF($A$1:$A$453,M69,$I$1:$I$453) -> 11
A70: 80870015 | B70: Whisper Panty Liners Reg 20pcs | C70: 3 | D70: 460.5 | E70: 2CANCEL | G70: 1 | H70: 2 | I70: =C70-H70 -> 1 | M70: 80870015 | N70: =SUMIF($A$1:$A$453,M70,$I$1:$I$453) -> 3
A71: 80870357 | B71: Whisper Super Absorbent M-L (Pack of 6) | C71: 101 | D71: 23464.32 | I71: =C71-H71 -> 101 | M71: 80870357 | N71: =SUMIF($A$1:$A$453,M71,$I$1:$I$453) -> 178
A72: 83916746 | B72: Whisper Ultra Night XXL - 21 Pads (7 pads x 3) | C72: 27 | D72: 2723.76 | I72: =C72-H72 -> 27 | M72: 83916746 | N72: =SUMIF($A$1:$A$453,M72,$I$1:$I$453) -> 57
A73: 80887674 | B73: Whisper Ultra Night XXXL Sanitary Pads - 8 pads (4 x 2) | C73: 12 | D73: 1578.96 | I73: =C73-H73 -> 12 | M73: 80887674 | N73: =SUMIF($A$1:$A$453,M73,$I$1:$I$453) -> 24
A74: 83914233 | B74: Whisper Ultra Soft XL Sanitary Pads - 18 pads (6 x 3) | C74: 15 | D74: 1081.2 | I74: =C74-H74 -> 15 | M74: 83914233 | N74: =SUMIF($A$1:$A$453,M74,$I$1:$I$453) -> 18
A75: 80893410 | B75: Whisper Ultra XL+ Sanitary Pads - 21 Pads (7 pads x 3) | C75: 39 | D75: 3478.41 | I75: =C75-H75 -> 39 | M75: 80893410 | N75: =SUMIF($A$1:$A$453,M75,$I$1:$I$453) -> 99
A76: 83904003 | B76: Gillette Cartridges ( 16 Cartridges) | C76: 12 | D76: 1322.4 | I76: =C76-H76 -> 12 | M76: 80866728 | N76: =SUMIF($A$1:$A$453,M76,$I$1:$I$453) -> 5
A77: 80867316 | B77: Gillette Guard 3-in-1 Blade Cartridge - 4 cartridge (2 x 2) | C77: 8 | D77: 707.12 | I77: =C77-H77 -> 8 | M77: 80866725 | N77: =SUMIF($A$1:$A$453,M77,$I$1:$I$453) -> 5
A78: 80896468 | B78: Gillette Guard Shaving Cream - 375gm (125gm x 3) | C78: 6 | D78: 297.6 | I78: =C78-H78 -> 6 | M78: 80818341 | N78: =SUMIF($A$1:$A$453,M78,$I$1:$I$453) -> 5
A79: 80876082 | B79: Gillette Mach3 Cartridge 2s | C79: 2 | D79: 623.2 | I79: =C79-H79 -> 2 | M79: 80830411 | N79: =SUMIF($A$1:$A$453,M79,$I$1:$I$453) -> 6
A80: 80862828 | B80: Gillette Regular Shaving Cream for Men - 279g (93g x 3) | C80: 3 | D80: 190.2 | I80: =C80-H80 -> 3 | M80: 80843635 | N80: =SUMIF($A$1:$A$453,M80,$I$1:$I$453) -> 1
A81: 80866728 | B81: Gillette Shaving Foam Charcoal 196g | C81: 2 | D81: 482.14 | I81: =C81-H81 -> 2 | M81: 80876990 | N81: =SUMIF($A$1:$A$453,M81,$I$1:$I$453) -> 2
A82: 80866725 | B82: Gillette Shaving Foam Classic Lemon 196g | C82: 1 | D82: 241.07 | I82: =C82-H82 -> 1 | M82: 83916219 | N82: =SUMIF($A$1:$A$453,M82,$I$1:$I$453) -> 8
A83: 80866723 | B83: Gillette Shaving Foam Classic Sensitive 418g | C83: 44 | D83: 11392.48 | I83: =C83-H83 -> 44 | M83: 80780342 | N83: =SUMIF($A$1:$A$453,M83,$I$1:$I$453) -> 1
A84: 80866729 | B84: Gillette Shaving Foam Classis Regular 418g | C84: 104 | D84: 26927.68 | G84: 1 | H84: 3 | I84: =C84-H84 -> 101 | M84: 80830097 | N84: =SUMIF($A$1:$A$453,M84,$I$1:$I$453) -> 5
A85: 80875507 | B85: Gillette Vector Razor - Pack of 2 | C85: 2 | D85: 187.48 | I85: =C85-H85 -> 2 | M85: 83908992 | N85: =SUMIF($A$1:$A$453,M85,$I$1:$I$453) -> 2
A86: 80864300 | B86: Gillette Vector Razor Cartridges - 4 pc (2 x 2) | C86: 2 | D86: 173.1 | I86: =C86-H86 -> 2 | M86: 80866727 | N86: =SUMIF($A$1:$A$453,M86,$I$1:$I$453) -> 1
A87: 80818341 | B87: Gillette Vector3 Razor | C87: 3 | D87: 468.78 | I87: =C87-H87 -> 3 | M87: 80803712 | N87: =SUMIF($A$1:$A$453,M87,$I$1:$I$453) -> 2
A88: 80875513 | B88: Gillette Venus Bikini Sensitive Razor | C88: 9 | D88: 1381.5 | I88: =C88-H88 -> 9 | M88: 83924708 | N88: =SUMIF($A$1:$A$453,M88,$I$1:$I$453) -> 40
A89: 80840354 | B89: Gillette Venus Comfortglide Razor 1 Pc | C89: 7 | D89: 2302.65 | I89: =C89-H89 -> 7 | M89: 83925440 | N89: =SUMIF($A$1:$A$453,M89,$I$1:$I$453) -> 44
A90: 80840352 | B90: Gillette Venus ComfortGlide Cartridges (2 pieces) | C90: 2 | D90: 833.34 | I90: =C90-H90 -> 2 | M90: 80895791 | N90: =SUMIF($A$1:$A$453,M90,$I$1:$I$453) -> 2
A91: 80864296 | B91: Gillette Venus Simply Razor - 3 Razors (1 x 3) | C91: 6 | D91: 521.1 | I91: =C91-H91 -> 6 | M91: 80739423 | N91: =SUMIF($A$1:$A$453,M91,$I$1:$I$453) -> 2
A92: 80864297 | B92: Gillette Venus Skin Love Razor - Pack of 1 | C92: 72 | D92: 11052 | I92: =C92-H92 -> 72 | M92: 80830420 | N92: =SUMIF($A$1:$A$453,M92,$I$1:$I$453) -> 1
A93: 80832389 | B93: Gillette Venus Smooth Sensitive Cartridges (2 pieces) | C93: 4 | D93: 1315.8 | I93: =C93-H93 -> 4 | M93: 80753180 | N93: =SUMIF($A$1:$A$453,M93,$I$1:$I$453) -> 3
A94: 80832398 | B94: Gillette Venus Smooth Sensitive Razor 1 Pc | C94: 4 | D94: 1140.36 | I94: =C94-H94 -> 4 | M94: 80818346 | N94: =SUMIF($A$1:$A$453,M94,$I$1:$I$453) -> 3
A95: 80832394 | B95: Gillette Venus Snap Razor, Pack of 1 | C95: 3 | D95: 1118.4 | I95: =C95-H95 -> 3 | M95: 83911268 | N95: =SUMIF($A$1:$A$453,M95,$I$1:$I$453) -> 18
A96: 83911270 | B96: H&S AHF Anti-Dandruff Shampoo (72 ml), Pack of 3 | C96: 24 | D96: 1723.44 | I96: =C96-H96 -> 24 | M96: 80894404 | N96: =SUMIF($A$1:$A$453,M96,$I$1:$I$453) -> 2
A97: 80892904 | B97: H&S CM Shampoo (72 ml), Pack of 3 | C97: 63 | D97: 4524.03 | F97: 1490839444785423 | I97: =C97-H97 -> 63 | M97: 80895482 | N97: =SUMIF($A$1:$A$453,M97,$I$1:$I$453) -> 2
A98: 83911280 | B98: H&S S&S Shampoo (72 ml), Pack of 3 | C98: 9 | D98: 646.29 | I98: =C98-H98 -> 9 | M98: 80895503 | N98: =SUMIF($A$1:$A$453,M98,$I$1:$I$453) -> 6
A99: 80880909 | B99: H&S S&S 2-in-1 Shampoo + Conditioner 72 ml, Pack of 3 | C99: 6 | D99: 463.62 | I99: =C99-H99 -> 6 | M99: 80885888 | N99: =SUMIF($A$1:$A$453,M99,$I$1:$I$453) -> 9
A100: 83911276 | B100: Head & Shoulders 7in1 Shampoo | 7 benefits , Pack of 3 | C100: 6 | D100: 430.86 | I100: =C100-H100 -> 6
...

Sheet 11-12_AUG
B1: SUB_BRAND | C1: EXPECTED | D1: ACTUAL | E1: DIFF
B2: Cream GIL Lime 93gm | C2: 6 | D2: 6 | E2: =C2-D2 -> 0
B3: AS SPLSH (RB) 50ML | C3: 2 | D3: 2 | E3: =C3-D3 -> 0
B4: Guard R+8 Promo Pack | C4: 152 | D4: 152 | E4: =C4-D4 -> 0
B5: Foam (Reg) 50gm | C5: 18 | D5: 18 | E5: =C5-D5 -> 0
B6: Fusion Power Raz | C6: 1 | D6: 1 | E6: =C6-D6 -> 0
B7: Fusion Raz | C7: 3 | D7: 3 | E7: =C7-D7 -> 0
B8: Guard 3in1 Cart 2s | C8: 18 | D8: 18 | E8: =C8-D8 -> 0
B9: Guard Cream 125 gm | C9: 60 | D9: 60 | E9: =C9-D9 -> 0
B10: Mach 3 Cart 2s | C10: 14 | D10: 14 | E10: =C10-D10 -> 0
B11: Mach-3 Charcoal Rzr | C11: 4 | D11: 4 | E11: =C11-D11 -> 0
B12: Cream GIL Reg 93gm | C12: 9 | D12: 9 | E12: =C12-D12 -> 0
B13: TSG (Sen) 60g | C13: 3 | D13: 3 | E13: =C13-D13 -> 0
... B97: Inhaler Keychain | C97: 9 | D97: 9 | E97: =C97-D97 -> 0
